{"ALEPH/USDT": {"last": 0.09053, "ask": 0.09065, "bid": 0.08846}, "OGN/USDT": {"last": 0.08929, "ask": 0.08947, "bid": 0.08924}, "DCERC/USDT": {"last": 0.0009116, "ask": 0.0009148, "bid": 0.000886}, "HC/USDT": {"last": 0.07401, "ask": 0.07492, "bid": 0.07384}, "HAM/USDT": {"last": 2.405e-09, "ask": 2.44e-09, "bid": 2.405e-09}, "QNT/USDT": {"last": 105.753, "ask": 105.923, "bid": 105.661}, "GMMT/USDT": {"last": 2.943, "ask": 2.945, "bid": 2.942}, "ALLIN/USDT": {"last": 2.203, "ask": 2.204, "bid": 2.2}, "HARD/USDT": {"last": 0.1426, "ask": 0.1426, "bid": 0.1422}, "GHNY/USDT": {"last": 11.84, "ask": 11.81, "bid": 11.58}, "TFI/USDT": {"last": 0.01169, "ask": 0.0119, "bid": 0.01163}, "AMG/USDT": {"last": 0.07936, "ask": 0.07956, "bid": 0.07881}, "SBR/USDT": {"last": 0.0007804, "ask": 0.0007851, "bid": 0.0007766}, "HAWK/USDT": {"last": 0.00162, "ask": 0.00162, "bid": 0.0016}, "KROM/USDT": {"last": 0.03236, "ask": 0.03299, "bid": 0.0321}, "ANT/USDT": {"last": 3.1575, "ask": 3.1661, "bid": 3.1525}, "XFT/USDT": {"last": 0.4076, "ask": 0.4184, "bid": 0.4065}, "Step Hero/USDT": {"last": 0.0006558, "ask": 0.0006649, "bid": 0.0006534}, "SOLX/USDT": {"last": 0.0004061, "ask": 0.0004111, "bid": 0.0004002}, "MTV/USDT": {"last": 0.0010458, "ask": 0.0010545, "bid": 0.0010357}, "MAN/USDT": {"last": 0.0188, "ask": 0.0188, "bid": 0.01808}, "MC/USDT": {"last": 0.2411, "ask": 0.2413, "bid": 0.2403}, "VET/USDT": {"last": 0.0190292, "ask": 0.0190169, "bid": 0.0189794}, "CNG/USDT": {"last": 0.07194, "ask": 0.08725, "bid": 0.07064}, "SPS/USDT": {"last": 0.02045, "ask": 0.02084, "bid": 0.02021}, "OPUL/USDT": {"last": 0.13365, "ask": 0.13535, "bid": 0.13343}, "DfiStarter/USDT": {"last": 0.003174, "ask": 0.003181, "bid": 0.003161}, "DGH/USDT": {"last": 0.00949, "ask": 0.01071, "bid": 0.00949}, "ARG/USDT": {"last": 0.7322, "ask": 0.737, "bid": 0.7316}, "DXGM/USDT": {"last": 0.010614, "ask": 0.010698, "bid": 0.01061}, "DUSK/USDT": {"last": 0.1397, "ask": 0.14, "bid": 0.1395}, "SWRV/USDT": {"last": 0.10717, "ask": 0.10791, "bid": 0.10574}, "ALGOBLK/USDT": {"last": 0.006016, "ask": 0.006134, "bid": 0.005935}, "MGOD/USDT": {"last": 0.003944, "ask": 0.004041, "bid": 0.003942}, "ASM/USDT": {"last": 1.077, "ask": 1.078, "bid": 1.061}, "RDNT/USDT": {"last": 0.2995, "ask": 0.3, "bid": 0.2947}, "CAS/USDT": {"last": 0.006365, "ask": 0.006392, "bid": 0.006295}, "QTZ/USDT": {"last": 0.00077, "ask": 0.0007843, "bid": 0.0007634}, "DAI/USDT": {"last": 0.9997, "ask": 0.9998, "bid": 0.9997}, "PYM/USDT": {"last": 0.001701, "ask": 0.001704, "bid": 0.001688}, "QUACKS/USDT": {"last": 7.6e-05, "ask": 7.25e-05, "bid": 7.01e-05}, "BNC/USDT": {"last": 0.19522, "ask": 0.19627, "bid": 0.19446}, "PIP/USDT": {"last": 0.2479, "ask": 0.2489, "bid": 0.2461}, "SKL/USDT": {"last": 0.03099, "ask": 0.03099, "bid": 0.0309}, "VRH/USDT": {"last": 0.01278, "ask": 0.01286, "bid": 0.01269}, "NETT/USDT": {"last": 0.172, "ask": 0.1835, "bid": 0.1681}, "COTI/USDT": {"last": 0.06857, "ask": 0.06876, "bid": 0.06859}, "ORT/USDT": {"last": 0.004437, "ask": 0.004449, "bid": 0.004445}, "HOLD/USDT": {"last": 1.366e-09, "ask": 1.367e-09, "bid": 1.365e-09}, "AVA/USDT": {"last": 0.543446, "ask": 0.545897, "bid": 0.543443}, "KILT/USDT": {"last": 0.3827, "ask": 0.3826, "bid": 0.3788}, "BRISE/USDT": {"last": 2.806e-07, "ask": 2.809e-07, "bid": 2.804e-07}, "BHD/USDT": {"last": 0.05635, "ask": 0.05645, "bid": 0.0557}, "SAUBER/USDT": {"last": 0.9962, "ask": 0.9997, "bid": 0.9735}, "FSN/USDT": {"last": 0.3486, "ask": 0.3523, "bid": 0.3457}, "AKITAX/USDT": {"last": 6.415e-05, "ask": 6.469e-05, "bid": 6.37e-05}, "API/USDT": {"last": 0.00188, "ask": 0.001892, "bid": 0.001825}, "PCX/USDT": {"last": 0.3415, "ask": 0.3505, "bid": 0.3386}, "XLS/USDT": {"last": 0.1203, "ask": 0.1395, "bid": 0.1192}, "MVD/USDT": {"last": 6.93, "ask": 6.99, "bid": 6.88}, "MCTP/USDT": {"last": 0.0152, "ask": 0.0162, "bid": 0.0148}, "FTT/USDT": {"last": 1.0815, "ask": 1.0916, "bid": 1.0834}, "PAXG/USDT": {"last": 2019.24, "ask": 2019.29, "bid": 2017.06}, "MLT/USDT": {"last": 0.15069, "ask": 0.15081, "bid": 0.15005}, "RBN/USDT": {"last": 0.1494, "ask": 0.15, "bid": 0.1481}, "TAI/USDT": {"last": 0.1726, "ask": 0.173, "bid": 0.1721}, "XAVA/USDT": {"last": 0.2857, "ask": 0.2906, "bid": 0.285}, "ZOA/USDT": {"last": 0.0008488, "ask": 0.0008495, "bid": 0.0008382}, "PBR/USDT": {"last": 0.04817, "ask": 0.04835, "bid": 0.047}, "PRQ/USDT": {"last": 0.08537, "ask": 0.08603, "bid": 0.08515}, "PSP/USDT": {"last": 0.03173, "ask": 0.03261, "bid": 0.03172}, "CBK/USDT": {"last": 0.5895, "ask": 0.5939, "bid": 0.5839}, "USDP/USDT": {"last": 0.9995, "ask": 0.9996, "bid": 0.9994}, "ALPINE/USDT": {"last": 2.278, "ask": 2.278, "bid": 2.271}, "BRDG/USDT": {"last": 0.000549, "ask": 0.000549, "bid": 0.000544}, "DEGO/USDT": {"last": 1.8449, "ask": 1.8542, "bid": 1.8493}, "Sin City Token/USDT": {"last": 0.005525, "ask": 0.005533, "bid": 0.005499}, "HATI/USDT": {"last": 3.786e-10, "ask": 3.917e-10, "bid": 3.732e-10}, "OCT/USDT": {"last": 0.1869, "ask": 0.1876, "bid": 0.1851}, "KZEN/USDT": {"last": 0.00195, "ask": 0.001954, "bid": 0.001938}, "CRDC/USDT": {"last": 0.001618, "ask": 0.001651, "bid": 0.001607}, "CLY/USDT": {"last": 0.04514, "ask": 0.04514, "bid": 0.04479}, "BORA/USDT": {"last": 0.1536, "ask": 0.1543, "bid": 0.1531}, "BOB/USDT": {"last": 4.121e-05, "ask": 4.181e-05, "bid": 4.13e-05}, "CHAMP/USDT": {"last": 0.04843, "ask": 0.04847, "bid": 0.04823}, "SIMPSON/USDT": {"last": 6.805e-12, "ask": 6.803e-12, "bid": 6.579e-12}, "FORT/USDT": {"last": 0.17165, "ask": 0.1738, "bid": 0.17151}, "MX/USDT": {"last": 2.6204, "ask": 2.6181, "bid": 2.6162}, "ROUTE/USDT": {"last": 2.519, "ask": 2.519, "bid": 2.471}, "VISION/USDT": {"last": 0.002064, "ask": 0.002065, "bid": 0.002064}, "KAKA/USDT": {"last": 0.0012096, "ask": 0.0012193, "bid": 0.0012}, "INS/USDT": {"last": 7.7e-06, "ask": 7.85e-06, "bid": 7.65e-06}, "RUSH/USDT": {"last": 0.001003, "ask": 0.001008, "bid": 0.001002}, "XI/USDT": {"last": 0.01247, "ask": 0.01278, "bid": 0.01209}, "CENX/USDT": {"last": 0.0005048, "ask": 0.0005062, "bid": 0.0004982}, "UNQ/USDT": {"last": 0.00176, "ask": 0.001789, "bid": 0.001675}, "WEC/USDT": {"last": 0.0254, "ask": 0.02558, "bid": 0.02516}, "THG/USDT": {"last": 0.05881, "ask": 0.05927, "bid": 0.05881}, "BDX/USDT": {"last": 0.04451, "ask": 0.04452, "bid": 0.04447}, "FLY/USDT": {"last": 0.0009128, "ask": 0.0009279, "bid": 0.0009034}, "RENA/USDT": {"last": 0.001667, "ask": 0.001666, "bid": 0.001633}, "GLO/USDT": {"last": 0.0002059, "ask": 0.000218, "bid": 0.0002059}, "SIMP/USDT": {"last": 0.00413, "ask": 0.00416, "bid": 0.0041}, "AUR/USDT": {"last": 0.9261, "ask": 0.9261, "bid": 0.9257}, "MTRX/USDT": {"last": 0.00183, "ask": 0.00184, "bid": 0.00183}, "WSB/USDT": {"last": 9.322e-08, "ask": 9.322e-08, "bid": 9.284e-08}, "TSUKA/USDT": {"last": 0.04271, "ask": 0.04271, "bid": 0.04266}, "XELS/USDT": {"last": 0.372, "ask": 0.3724, "bid": 0.37}, "PIG/USDT": {"last": 1.63e-08, "ask": 1.639e-08, "bid": 1.618e-08}, "SAFE/USDT": {"last": 7.872, "ask": 7.905, "bid": 7.846}, "DRAW/USDT": {"last": 0.000229, "ask": 0.000231, "bid": 0.0002286}, "THN/USDT": {"last": 0.034208, "ask": 0.034229, "bid": 0.034142}, "X2Y2/USDT": {"last": 0.02938, "ask": 0.02941, "bid": 0.0293}, "HOTCROSS/USDT": {"last": 0.003224, "ask": 0.003225, "bid": 0.003208}, "POT/USDT": {"last": 0.00477, "ask": 0.004802, "bid": 0.004709}, "XVS/USDT": {"last": 4.811, "ask": 4.821, "bid": 4.802}, "WAVES/USDT": {"last": 1.548, "ask": 1.548, "bid": 1.542}, "MEV/USDT": {"last": 0.00649, "ask": 0.0067, "bid": 0.00647}, "PEOPLE/USDT": {"last": 0.01771, "ask": 0.01776, "bid": 0.0177}, "POLC/USDT": {"last": 0.01622, "ask": 0.01632, "bid": 0.01615}, "UNO/USDT": {"last": 0.05103, "ask": 0.05155, "bid": 0.0506}, "FODL/USDT": {"last": 0.002657, "ask": 0.002687, "bid": 0.002649}, "Pros.Finance/USDT": {"last": 0.3649, "ask": 0.4033, "bid": 0.3648}, "HTE/USDT": {"last": 0.003183, "ask": 0.004001, "bid": 0.00319}, "METABABY/USDT": {"last": 0.01102, "ask": 0.01097, "bid": 0.00974}, "ZPAY/USDT": {"last": 0.064, "ask": 0.06491, "bid": 0.06369}, "AIEN/USDT": {"last": 2.038e-09, "ask": 2.039e-09, "bid": 2.025e-09}, "CLB/USDT": {"last": 0.00181, "ask": 0.00182, "bid": 0.00179}, "RISE/USDT": {"last": 0.0001258, "ask": 0.000126, "bid": 0.0001185}, "SPRT/USDT": {"last": 0.0012, "ask": 0.0012, "bid": 0.001}, "OPV/USDT": {"last": 0.21807, "ask": 0.21874, "bid": 0.21786}, "TTC/USDT": {"last": 0.11217, "ask": 0.11217, "bid": 0.11216}, "RING/USDT": {"last": 0.003622, "ask": 0.003682, "bid": 0.003614}, "FIRO/USDT": {"last": 1.712, "ask": 1.712, "bid": 1.705}, "SLP/USDT": {"last": 0.002162, "ask": 0.002162, "bid": 0.002157}, "TKB/USDT": {"last": 0.00109, "ask": 0.001092, "bid": 0.001089}, "XP/USDT": {"last": 0.05453, "ask": 0.05476, "bid": 0.05453}, "POPK/USDT": {"last": 0.003136, "ask": 0.003277, "bid": 0.003067}, "MIR/USDT": {"last": 0.06268, "ask": 0.06274, "bid": 0.06262}, "SHIT/USDT": {"last": 9.146e-09, "ask": 9.159e-09, "bid": 8.845e-09}, "WAXL/USDT": {"last": 0.5332, "ask": 0.5307, "bid": 0.5294}, "DAR/USDT": {"last": 0.1323, "ask": 0.1325, "bid": 0.132}, "KSM/USDT": {"last": 24.8166, "ask": 24.9251, "bid": 24.8404}, "HELMET/USDT": {"last": 0.006776, "ask": 0.006875, "bid": 0.006738}, "QTUM/USDT": {"last": 2.5701, "ask": 2.5716, "bid": 2.5682}, "WNK/USDT": {"last": 0.0008617, "ask": 0.0008618, "bid": 0.0008612}, "BXX/USDT": {"last": 0.01846, "ask": 0.01846, "bid": 0.01839}, "AGV/USDT": {"last": 0.0003728, "ask": 0.000384, "bid": 0.0003729}, "RVN/USDT": {"last": 0.0202, "ask": 0.02029, "bid": 0.02022}, "NOS/USDT": {"last": 0.0154, "ask": 0.01541, "bid": 0.0154}, "USDN/USDT": {"last": 0.03678, "ask": 0.03698, "bid": 0.03573}, "STABLZ/USDT": {"last": 0.0166, "ask": 0.0167, "bid": 0.0164}, "ARW/USDT": {"last": 0.1166, "ask": 0.1257, "bid": 0.1166}, "ONE/USDT": {"last": 0.01582, "ask": 0.01588, "bid": 0.01583}, "BOW/USDT": {"last": 0.641, "ask": 0.668, "bid": 0.597}, "MSB/USDT": {"last": 0.00668, "ask": 0.00668, "bid": 0.00608}, "GRND/USDT": {"last": 0.13907, "ask": 0.13965, "bid": 0.1387}, "CHRP/USDT": {"last": 0.005215, "ask": 0.005242, "bid": 0.005185}, "WIT/USDT": {"last": 0.005803, "ask": 0.005842, "bid": 0.00571}, "ING/USDT": {"last": 0.0008197, "ask": 0.0008205, "bid": 0.0008151}, "MCC/USDT": {"last": 8.166e-05, "ask": 8.467e-05, "bid": 8.164e-05}, "ITHEUM/USDT": {"last": 0.03547, "ask": 0.03558, "bid": 0.03538}, "DMG/USDT": {"last": 0.002304, "ask": 0.002324, "bid": 0.0023}, "DMS/USDT": {"last": 9.744e-05, "ask": 9.939e-05, "bid": 9.714e-05}, "WIFI/USDT": {"last": 0.03774, "ask": 0.03791, "bid": 0.03767}, "ONX/USDT": {"last": 0.03224, "ask": 0.03313, "bid": 0.03205}, "VELA/USDT": {"last": 2.457, "ask": 2.462, "bid": 2.453}, "WRLD/USDT": {"last": 0.032911, "ask": 0.03297, "bid": 0.032181}, "ZENI/USDT": {"last": 0.003992, "ask": 0.003999, "bid": 0.003882}, "SOON/USDT": {"last": 0.02417, "ask": 0.02429, "bid": 0.02414}, "BVG/USDT": {"last": 0.0855, "ask": 0.08928, "bid": 0.08551}, "CTK/USDT": {"last": 0.7276, "ask": 0.7299, "bid": 0.7273}, "JAB/USDT": {"last": 0.0626, "ask": 0.06265, "bid": 0.06255}, "CROWN/USDT": {"last": 1.302, "ask": 1.266, "bid": 1.259}, "DARC/USDT": {"last": 0.001193, "ask": 0.00122, "bid": 0.001164}, "ANV/USDT": {"last": 0.02645, "ask": 0.0265, "bid": 0.02636}, "IRIS/USDT": {"last": 0.02163, "ask": 0.02165, "bid": 0.02159}, "CEJI/USDT": {"last": 0.003129, "ask": 0.003157, "bid": 0.0031}, "AME/USDT": {"last": 0.001696, "ask": 0.00171, "bid": 0.00167}, "PLASTIK/USDT": {"last": 0.05827, "ask": 0.05999, "bid": 0.05746}, "TMTG/USDT": {"last": 7.94e-05, "ask": 8.141e-05, "bid": 7.937e-05}, "DEBT/USDT": {"last": 8.732, "ask": 8.774, "bid": 8.687}, "SFUND/USDT": {"last": 1.0179, "ask": 1.0272, "bid": 1.0218}, "ZKP/USDT": {"last": 0.02665, "ask": 0.02682, "bid": 0.02655}, "GEAR/USDT": {"last": 0.006202, "ask": 0.00621, "bid": 0.00601}, "CROGE/USDT": {"last": 0.000533, "ask": 0.000618, "bid": 0.000531}, "LYRA/USDT": {"last": 0.07744, "ask": 0.07749, "bid": 0.07675}, "NFT/USDT": {"last": 3.559e-07, "ask": 3.582e-07, "bid": 3.525e-07}, "SOLO/USDT": {"last": 0.121, "ask": 0.1213, "bid": 0.121}, "AMP/USDT": {"last": 0.002981, "ask": 0.002983, "bid": 0.002973}, "LITT/USDT": {"last": 0.00712, "ask": 0.0072, "bid": 0.00693}, "BAX/USDT": {"last": 0.00027999, "ask": 0.00028261, "bid": 0.00027206}, "SPONGE/USDT": {"last": 0.0005796, "ask": 0.00058, "bid": 0.0005796}, "O3/USDT": {"last": 0.05042, "ask": 0.05062, "bid": 0.04956}, "VNLNK/USDT": {"last": 4.7e-06, "ask": 4.94e-06, "bid": 4.7e-06}, "SHILL/USDT": {"last": 0.01113, "ask": 0.01128, "bid": 0.01111}, "KUNCI/USDT": {"last": 0.010168, "ask": 0.010643, "bid": 0.010168}, "IDEA/USDT": {"last": 0.00541, "ask": 0.005433, "bid": 0.005349}, "FAVOR/USDT": {"last": 0.0479, "ask": 0.0491, "bid": 0.0466}, "METO/USDT": {"last": 0.001141, "ask": 0.001151, "bid": 0.001132}, "SOFI/USDT": {"last": 0.07201, "ask": 0.07201, "bid": 0.0712}, "POLO/USDT": {"last": 0.0002152, "ask": 0.0002179, "bid": 0.0002132}, "VRT/USDT": {"last": 0.0003717, "ask": 0.0003782, "bid": 0.00037}, "MNR/USDT": {"last": 0.001184, "ask": 0.001248, "bid": 0.001048}, "TRCL/USDT": {"last": 0.00105, "ask": 0.001073, "bid": 0.0009878}, "GST/USDT": {"last": 0.0157, "ask": 0.01583, "bid": 0.01564}, "KIBA/USDT": {"last": 2.22e-06, "ask": 2.289e-06, "bid": 2.222e-06}, "SCOTTY/USDT": {"last": 0.001015, "ask": 0.001018, "bid": 0.00101}, "CHESS/USDT": {"last": 0.1783, "ask": 0.1785, "bid": 0.178}, "COLLAB/USDT": {"last": 0.01174, "ask": 0.01175, "bid": 0.01172}, "IGU/USDT": {"last": 0.03983, "ask": 0.04037, "bid": 0.03901}, "TRG/USDT": {"last": 1.717e-07, "ask": 1.72e-07, "bid": 1.701e-07}, "EPK/USDT": {"last": 0.011108, "ask": 0.011136, "bid": 0.011089}, "UNIX/USDT": {"last": 0.0179, "ask": 0.01804, "bid": 0.01771}, "PEX/USDT": {"last": 0.05776, "ask": 0.05871, "bid": 0.05773}, "SGT/USDT": {"last": 1.0152, "ask": 0.9849, "bid": 0.9361}, "MYST/USDT": {"last": 0.2545, "ask": 0.2572, "bid": 0.2515}, "WOOF/USDT": {"last": 0.0002995, "ask": 0.0003044, "bid": 0.0002983}, "ZZZ/USDT": {"last": 0.36944, "ask": 0.37001, "bid": 0.3664}, "CHO/USDT": {"last": 0.197, "ask": 0.1977, "bid": 0.1962}, "HIGH/USDT": {"last": 1.489, "ask": 1.489, "bid": 1.481}, "ALF/USDT": {"last": 0.000301, "ask": 0.000321, "bid": 0.000294}, "MECHA/USDT": {"last": 0.121, "ask": 0.158, "bid": 0.1211}, "YAE/USDT": {"last": 0.00525, "ask": 0.00526, "bid": 0.00507}, "ROSE/USDT": {"last": 0.0524, "ask": 0.05255, "bid": 0.05237}, "DEVO/USDT": {"last": 0.00255, "ask": 0.002801, "bid": 0.002601}, "WOO/USDT": {"last": 0.2296, "ask": 0.2297, "bid": 0.2295}, "VTHO/USDT": {"last": 0.0012574, "ask": 0.001262, "bid": 0.0012562}, "LAMB/USDT": {"last": 0.001611, "ask": 0.001612, "bid": 0.001606}, "PIB/USDT": {"last": 0.0002916, "ask": 0.0002993, "bid": 0.000283}, "PLT/USDT": {"last": 2.593, "ask": 2.606, "bid": 2.59}, "BOTTO/USDT": {"last": 0.1291, "ask": 0.1338, "bid": 0.1287}, "EOS3S/USDT": {"last": 0.669846, "ask": 0.670069, "bid": 0.668728}, "LBLOCK/USDT": {"last": 0.0001639, "ask": 0.0001639, "bid": 0.00015}, "MEAN/USDT": {"last": 0.02389, "ask": 0.02424, "bid": 0.02381}, "EMON/USDT": {"last": 0.001596, "ask": 0.001616, "bid": 0.001578}, "HIFI/USDT": {"last": 0.3485, "ask": 0.3488, "bid": 0.3457}, "FXS/USDT": {"last": 6.406, "ask": 6.417, "bid": 6.406}, "SELLC/USDT": {"last": 0.02268, "ask": 0.02307, "bid": 0.02256}, "FACTR/USDT": {"last": 0.04115, "ask": 0.04169, "bid": 0.04098}, "FNCY/USDT": {"last": 0.0324, "ask": 0.03225, "bid": 0.03213}, "WBT/USDT": {"last": 4.67, "ask": 4.67, "bid": 4.669}, "NHCT/USDT": {"last": 0.05846, "ask": 0.05869, "bid": 0.05741}, "INJ/USDT": {"last": 6.079, "ask": 6.08, "bid": 6.077}, "KXA/USDT": {"last": 0.008291, "ask": 0.008324, "bid": 0.008291}, "CRV/USDT": {"last": 0.8053, "ask": 0.8075, "bid": 0.8035}, "NNT/USDT": {"last": 0.0061, "ask": 0.00613, "bid": 0.006}, "1MIL/USDT": {"last": 0.28176, "ask": 0.2849, "bid": 0.27728}, "CLOAK/USDT": {"last": 0.005366, "ask": 0.005391, "bid": 0.005315}, "APED/USDT": {"last": 1.358, "ask": 1.397, "bid": 1.358}, "CHS/USDT": {"last": 0.06269, "ask": 0.06269, "bid": 0.05993}, "DGC/USDT": {"last": 0.0004077, "ask": 0.0004104, "bid": 0.0004075}, "AZY/USDT": {"last": 0.0105, "ask": 0.0105, "bid": 0.0101}, "MMO/USDT": {"last": 0.07818, "ask": 0.0785, "bid": 0.07796}, "MSTR/USDT": {"last": 0.109, "ask": 0.1097, "bid": 0.1088}, "MFI/USDT": {"last": 0.02185, "ask": 0.02197, "bid": 0.02179}, "UMB/USDT": {"last": 0.011251, "ask": 0.011365, "bid": 0.011155}, "HUAHUA/USDT": {"last": 6.554e-05, "ask": 6.554e-05, "bid": 6.319e-05}, "PANDAI/USDT": {"last": 3.21e-08, "ask": 3.221e-08, "bid": 3.202e-08}, "KOL/USDT": {"last": 0.004377, "ask": 0.00447, "bid": 0.004375}, "NUM/USDT": {"last": 0.02902, "ask": 0.02908, "bid": 0.029}, "SDN/USDT": {"last": 0.2418, "ask": 0.2494, "bid": 0.2416}, "BRKL/USDT": {"last": 0.013916, "ask": 0.014265, "bid": 0.013916}, "CVR/USDT": {"last": 0.00109, "ask": 0.00109, "bid": 0.00108}, "CTY/USDT": {"last": 22.959, "ask": 23.517, "bid": 22.827}, "CWAR/USDT": {"last": 0.01062, "ask": 0.01062, "bid": 0.01031}, "EDE/USDT": {"last": 1.0596, "ask": 1.0699, "bid": 1.0516}, "WILD/USDT": {"last": 0.2465, "ask": 0.2472, "bid": 0.2451}, "SPARTA/USDT": {"last": 0.008642, "ask": 0.008808, "bid": 0.00862}, "BNX/USDT": {"last": 0.4814, "ask": 0.4846, "bid": 0.4813}, "LSC/USDT": {"last": 1.426, "ask": 1.446, "bid": 1.425}, "SWEAT/USDT": {"last": 0.006418, "ask": 0.006432, "bid": 0.006412}, "NVIR/USDT": {"last": 0.03765, "ask": 0.03766, "bid": 0.03739}, "BIT1/USDT": {"last": 4.956e-06, "ask": 4.98e-06, "bid": 4.93e-06}, "PSI/USDT": {"last": 1.062, "ask": 1.089, "bid": 1.057}, "POMERIUM/USDT": {"last": 0.2544, "ask": 0.2565, "bid": 0.2544}, "SONNE/USDT": {"last": 0.08515, "ask": 0.08577, "bid": 0.08438}, "MTRM/USDT": {"last": 0.1182, "ask": 0.1242, "bid": 0.1235}, "PAXW/USDT": {"last": 0.00325, "ask": 0.00325, "bid": 0.00284}, "CNAME/USDT": {"last": 0.0004108, "ask": 0.0004225, "bid": 0.0004104}, "SHDW/USDT": {"last": 0.255, "ask": 0.297, "bid": 0.262}, "MOH/USDT": {"last": 0.0466, "ask": 0.0494, "bid": 0.0433}, "CRETA/USDT": {"last": 0.02707, "ask": 0.02766, "bid": 0.02706}, "ASTRO/USDT": {"last": 0.001146, "ask": 0.001146, "bid": 0.001122}, "ZCX/USDT": {"last": 0.06738, "ask": 0.06749, "bid": 0.06705}, "GLQ/USDT": {"last": 0.006015, "ask": 0.006073, "bid": 0.006006}, "ALYA/USDT": {"last": 0.01298, "ask": 0.01298, "bid": 0.01287}, "AERGO/USDT": {"last": 0.10805, "ask": 0.10891, "bid": 0.10795}, "EOS3L/USDT": {"last": 0.150995, "ask": 0.1513, "bid": 0.150995}, "INST/USDT": {"last": 1.3384, "ask": 1.3765, "bid": 1.3348}, "API3/USDT": {"last": 1.303, "ask": 1.303, "bid": 1.3}, "LOON/USDT": {"last": 0.005424, "ask": 0.005499, "bid": 0.005206}, "AE/USDT": {"last": 0.05195, "ask": 0.0521, "bid": 0.05148}, "NXTT/USDT": {"last": 0.000321, "ask": 0.000326, "bid": 0.000321}, "SMART/USDT": {"last": 0.23, "ask": 0.242, "bid": 0.23}, "XCN/USDT": {"last": 0.001896, "ask": 0.001902, "bid": 0.001885}, "BRT/USDT": {"last": 0.001506, "ask": 0.001512, "bid": 0.00149}, "PSL/USDT": {"last": 0.000315, "ask": 0.0003198, "bid": 0.0003147}, "PEPES/USDT": {"last": 3.579e-05, "ask": 3.707e-05, "bid": 3.533e-05}, "AZERO/USDT": {"last": 1.1048, "ask": 1.1048, "bid": 1.1047}, "MRST/USDT": {"last": 0.003732, "ask": 0.00376, "bid": 0.003722}, "SHIRYO/USDT": {"last": 5.263e-12, "ask": 5.263e-12, "bid": 5.088e-12}, "FNZ/USDT": {"last": 0.00316, "ask": 0.00318, "bid": 0.00308}, "SG/USDT": {"last": 0.01902, "ask": 0.02034, "bid": 0.01905}, "MILO/USDT": {"last": 7.35e-09, "ask": 7.61e-09, "bid": 7.25e-09}, "OAS/USDT": {"last": 0.07416, "ask": 0.07437, "bid": 0.07414}, "BEN/USDT": {"last": 4.1e-08, "ask": 4.1e-08, "bid": 4.041e-08}, "GOTG/USDT": {"last": 0.0869, "ask": 0.0876, "bid": 0.0859}, "SRT/USDT": {"last": 5.82e-05, "ask": 5.83e-05, "bid": 5.5e-05}, "IHC/USDT": {"last": 4.955e-05, "ask": 5.019e-05, "bid": 4.954e-05}, "TRADE/USDT": {"last": 0.15131, "ask": 0.15392, "bid": 0.15051}, "WATT/USDT": {"last": 0.007231, "ask": 0.007224, "bid": 0.007201}, "SCCP/USDT": {"last": 0.3377, "ask": 0.3442, "bid": 0.3374}, "POLS/USDT": {"last": 0.36209, "ask": 0.36378, "bid": 0.36229}, "GXT/USDT": {"last": 0.0005235, "ask": 0.0005312, "bid": 0.000512}, "NPT/USDT": {"last": 0.679, "ask": 0.689, "bid": 0.679}, "MTA/USDT": {"last": 0.02838, "ask": 0.02849, "bid": 0.02836}, "ARTIC/USDT": {"last": 0.022, "ask": 0.0224, "bid": 0.0218}, "YESP/USDT": {"last": 0.0026, "ask": 0.00265, "bid": 0.00255}, "MAP/USDT": {"last": 0.01289, "ask": 0.0129, "bid": 0.01288}, "KOLNET/USDT": {"last": 0.000409, "ask": 0.000414, "bid": 0.000399}, "MCRT/USDT": {"last": 0.002263, "ask": 0.002271, "bid": 0.002262}, "SPFC/USDT": {"last": 0.2321, "ask": 0.2406, "bid": 0.2304}, "GZONE/USDT": {"last": 0.02231, "ask": 0.024, "bid": 0.02214}, "PET/USDT": {"last": 0.1508, "ask": 0.15166, "bid": 0.15054}, "ORD/USDT": {"last": 3.262e-06, "ask": 3.3e-06, "bid": 3.261e-06}, "PAC/USDT": {"last": 4.654e-05, "ask": 4.668e-05, "bid": 4.651e-05}, "LED/USDT": {"last": 0.0246, "ask": 0.0232, "bid": 0.0223}, "CPH/USDT": {"last": 0.01549, "ask": 0.01553, "bid": 0.01527}, "SDEX/USDT": {"last": 0.002705, "ask": 0.002718, "bid": 0.002695}, "DSP/USDT": {"last": 0.02986, "ask": 0.03012, "bid": 0.02951}, "AMB/USDT": {"last": 0.00922, "ask": 0.00976, "bid": 0.00961}, "ASTRA/USDT": {"last": 0.0569, "ask": 0.0572, "bid": 0.0569}, "GMX/USDT": {"last": 60.59, "ask": 60.64, "bid": 60.59}, "VADER/USDT": {"last": 3.504e-05, "ask": 3.536e-05, "bid": 3.504e-05}, "CHE/USDT": {"last": 0.02996, "ask": 0.03026, "bid": 0.0297}, "CAND/USDT": {"last": 0.4113, "ask": 0.4128, "bid": 0.4069}, "CRA/USDT": {"last": 0.001127, "ask": 0.001129, "bid": 0.0011}, "GTC/USDT": {"last": 1.37, "ask": 1.371, "bid": 1.368}, "SXP/USDT": {"last": 0.4331, "ask": 0.4346, "bid": 0.4326}, "CITY/USDT": {"last": 5.339, "ask": 5.448, "bid": 5.355}, "MOBX/USDT": {"last": 0.07451, "ask": 0.07572, "bid": 0.07346}, "VNN/USDT": {"last": 0.03425, "ask": 0.03433, "bid": 0.03413}, "SKOLL/USDT": {"last": 6.38e-10, "ask": 6.438e-10, "bid": 6.336e-10}, "AOS/USDT": {"last": 6.063e-05, "ask": 6.088e-05, "bid": 5.946e-05}, "OKA/USDT": {"last": 0.0058, "ask": 0.0058, "bid": 0.0054}, "REI/USDT": {"last": 0.02308, "ask": 0.02314, "bid": 0.02305}, "SRM/USDT": {"last": 0.07739, "ask": 0.0779, "bid": 0.0774}, "MEMEME/USDT": {"last": 2.0053e-05, "ask": 2.0689e-05, "bid": 2.0053e-05}, "UFT/USDT": {"last": 0.3542, "ask": 0.3548, "bid": 0.3536}, "BRUH/USDT": {"last": 4.078e-08, "ask": 4.08e-08, "bid": 3.962e-08}, "RIDE/USDT": {"last": 0.027, "ask": 0.02695, "bid": 0.0256}, "T/USDT": {"last": 0.02715, "ask": 0.02724, "bid": 0.02712}, "STI/USDT": {"last": 0.002, "ask": 0.002004, "bid": 0.002}, "ACK/USDT": {"last": 0.011136, "ask": 0.011137, "bid": 0.010806}, "FLM/USDT": {"last": 0.08028, "ask": 0.0805, "bid": 0.08028}, "VITY/USDT": {"last": 9.112e-08, "ask": 9.922e-08, "bid": 9.115e-08}, "POPCOIN/USDT": {"last": 4.9e-07, "ask": 5.2e-07, "bid": 4.9e-07}, "BOND/USDT": {"last": 3.72, "ask": 3.72, "bid": 3.718}, "TARA/USDT": {"last": 0.001015, "ask": 0.0010201, "bid": 0.001005}, "DSLA/USDT": {"last": 0.0016798, "ask": 0.0017095, "bid": 0.0016773}, "PRTG/USDT": {"last": 5.436, "ask": 5.552, "bid": 5.415}, "QUICK/USDT": {"last": 58.899, "ask": 59.292, "bid": 58.866}, "XPNET/USDT": {"last": 0.003799, "ask": 0.003812, "bid": 0.003784}, "NVT/USDT": {"last": 0.00978, "ask": 0.00979, "bid": 0.00977}, "LAZIO/USDT": {"last": 2.393, "ask": 2.395, "bid": 2.388}, "LOOM/USDT": {"last": 0.05191, "ask": 0.05202, "bid": 0.05186}, "WSG/USDT": {"last": 1.525e-09, "ask": 1.53e-09, "bid": 1.52e-09}, "OGY/USDT": {"last": 0.00836, "ask": 0.00891, "bid": 0.00835}, "AURA/USDT": {"last": 0.06705, "ask": 0.06812, "bid": 0.06706}, "TAMA/USDT": {"last": 0.016633, "ask": 0.016641, "bid": 0.016487}, "RET/USDT": {"last": 1.681e-10, "ask": 1.788e-10, "bid": 1.683e-10}, "PLCUC/USDT": {"last": 143.57, "ask": 143.7, "bid": 143.38}, "UNIC/USDT": {"last": 2.987, "ask": 3.015, "bid": 2.985}, "IBFK/USDT": {"last": 1.3036, "ask": 1.3042, "bid": 1.3031}, "BLOK/USDT": {"last": 0.002015, "ask": 0.002012, "bid": 0.002}, "BPC/USDT": {"last": 0.01641, "ask": 0.01612, "bid": 0.01603}, "KUJI/USDT": {"last": 0.6223, "ask": 0.6278, "bid": 0.6157}, "EFC/USDT": {"last": 0.5217, "ask": 0.5312, "bid": 0.521}, "CGG/USDT": {"last": 0.05437, "ask": 0.05454, "bid": 0.05426}, "THB/USDT": {"last": 0.003, "ask": 0.003, "bid": 0.0028}, "NAV/USDT": {"last": 0.04771, "ask": 0.04785, "bid": 0.04601}, "DIP/USDT": {"last": 0.019505, "ask": 0.019594, "bid": 0.019347}, "DPET/USDT": {"last": 0.03605, "ask": 0.03636, "bid": 0.03604}, "WOM/USDT": {"last": 0.1151, "ask": 0.1156, "bid": 0.1151}, "RIF/USDT": {"last": 0.1328, "ask": 0.1342, "bid": 0.1317}, "BENQI/USDT": {"last": 0.007804, "ask": 0.007811, "bid": 0.007804}, "LAT/USDT": {"last": 0.007885, "ask": 0.007907, "bid": 0.007872}, "ITGR/USDT": {"last": 0.01419, "ask": 0.0144, "bid": 0.01408}, "MASS/USDT": {"last": 0.003713, "ask": 0.003763, "bid": 0.003701}, "RAZOR/USDT": {"last": 0.006414, "ask": 0.006518, "bid": 0.0064}, "MTR/USDT": {"last": 0.7368, "ask": 0.7392, "bid": 0.7356}, "NKN/USDT": {"last": 0.09377, "ask": 0.09397, "bid": 0.09376}, "HYPC/USDT": {"last": 0.31333, "ask": 0.31762, "bid": 0.31373}, "SWASH/USDT": {"last": 0.01504, "ask": 0.01513, "bid": 0.01502}, "POR/USDT": {"last": 0.7528, "ask": 0.7561, "bid": 0.7479}, "MTD/USDT": {"last": 0.1446, "ask": 0.1479, "bid": 0.1445}, "DERI/USDT": {"last": 0.01327, "ask": 0.01349, "bid": 0.01325}, "UP/USDT": {"last": 0.8206, "ask": 0.825, "bid": 0.8201}, "CRTS/USDT": {"last": 0.000174, "ask": 0.000174, "bid": 0.000162}, "PLUG/USDT": {"last": 0.001304, "ask": 0.001308, "bid": 0.001257}, "BTC3S/USDT": {"last": 0.014284, "ask": 0.014429, "bid": 0.01431}, "BFLY/USDT": {"last": 0.01748, "ask": 0.01831, "bid": 0.01748}, "MCADE/USDT": {"last": 0.01898, "ask": 0.01907, "bid": 0.01886}, "LOOKS/USDT": {"last": 0.07274, "ask": 0.07297, "bid": 0.07257}, "TRUSTFI/USDT": {"last": 0.01772, "ask": 0.017925, "bid": 0.017357}, "BIST/USDT": {"last": 0.02111, "ask": 0.02118, "bid": 0.02101}, "JOYSTICK/USDT": {"last": 0.0454, "ask": 0.04598, "bid": 0.04483}, "ETH3L/USDT": {"last": 0.382723, "ask": 0.383555, "bid": 0.381694}, "AVL/USDT": {"last": 1.1966, "ask": 1.2425, "bid": 1.182}, "SUIP/USDT": {"last": 0.22344, "ask": 0.22447, "bid": 0.22008}, "MBX/USDT": {"last": 0.899, "ask": 0.902, "bid": 0.896}, "STND/USDT": {"last": 0.01618, "ask": 0.01628, "bid": 0.01609}, "AX/USDT": {"last": 1.446, "ask": 1.449, "bid": 1.44}, "IMGNAI/USDT": {"last": 0.00959, "ask": 0.00965, "bid": 0.00948}, "LTC3L/USDT": {"last": 0.056806, "ask": 0.057411, "bid": 0.056744}, "LPT/USDT": {"last": 4.766, "ask": 4.778, "bid": 4.762}, "CWS/USDT": {"last": 0.2877, "ask": 0.2896, "bid": 0.2877}, "WBTC/USDT": {"last": 26508.1, "ask": 26542.5, "bid": 26507.9}, "LOVEDEESSE/USDT": {"last": 0.000691, "ask": 0.000761, "bid": 0.000648}, "KSC/USDT": {"last": 0.001398, "ask": 0.001398, "bid": 0.001289}, "SBCC/USDT": {"last": 0.28987, "ask": 0.30284, "bid": 0.28987}, "PINK/USDT": {"last": 0.001571, "ask": 0.001578, "bid": 0.001571}, "SML/USDT": {"last": 0.00599, "ask": 0.00603, "bid": 0.00599}, "ATH/USDT": {"last": 0.06399, "ask": 0.06399, "bid": 0.06216}, "PIVN/USDT": {"last": 0.02108, "ask": 0.02114, "bid": 0.02103}, "SHOOTER/USDT": {"last": 0.0006631, "ask": 0.00067, "bid": 0.0006632}, "PMON/USDT": {"last": 0.3498, "ask": 0.3631, "bid": 0.3486}, "MOVE/USDT": {"last": 4.375e-06, "ask": 4.463e-06, "bid": 4.259e-06}, "SLG/USDT": {"last": 0.02053, "ask": 0.02116, "bid": 0.02018}, "D3D/USDT": {"last": 0.09805, "ask": 0.0984, "bid": 0.098}, "USDD/USDT": {"last": 0.9991, "ask": 1.0001, "bid": 0.9981}, "FUND/USDT": {"last": 0.1548, "ask": 0.1548, "bid": 0.1541}, "GDG/USDT": {"last": 8e-05, "ask": 9e-05, "bid": 8e-05}, "BEL/USDT": {"last": 0.6294, "ask": 0.6295, "bid": 0.6286}, "BFR/USDT": {"last": 0.1054, "ask": 0.1064, "bid": 0.1047}, "HGHG/USDT": {"last": 0.006778, "ask": 0.006912, "bid": 0.006774}, "UMEE/USDT": {"last": 0.00606, "ask": 0.00607, "bid": 0.006011}, "FEI/USDT": {"last": 0.9555, "ask": 0.9647, "bid": 0.955}, "ALEX/USDT": {"last": 0.143, "ask": 0.1451, "bid": 0.143}, "OVR/USDT": {"last": 0.2804, "ask": 0.2813, "bid": 0.28}, "BOBA/USDT": {"last": 0.1705, "ask": 0.1739, "bid": 0.1706}, "APCG/USDT": {"last": 0.00596, "ask": 0.00601, "bid": 0.00591}, "SER/USDT": {"last": 0.002254, "ask": 0.002354, "bid": 0.002245}, "OPIUM/USDT": {"last": 0.12325, "ask": 0.12541, "bid": 0.12274}, "TYRANT/USDT": {"last": 0.1179, "ask": 0.1218, "bid": 0.1155}, "LDO/USDT": {"last": 1.892, "ask": 1.9, "bid": 1.882}, "DKS/USDT": {"last": 0.0010119, "ask": 0.0010189, "bid": 0.0010109}, "LITH/USDT": {"last": 0.000579, "ask": 0.000586, "bid": 0.0005774}, "NTVRK/USDT": {"last": 0.1468, "ask": 0.1522, "bid": 0.141}, "RLY/USDT": {"last": 0.00812, "ask": 0.008244, "bid": 0.008084}, "METAV/USDT": {"last": 0.00461, "ask": 0.00478, "bid": 0.00471}, "AR/USDT": {"last": 6.472, "ask": 6.462, "bid": 6.447}, "HCT/USDT": {"last": 0.000262, "ask": 0.0002634, "bid": 0.0002617}, "BZZ/USDT": {"last": 0.4301, "ask": 0.4304, "bid": 0.4293}, "VHC/USDT": {"last": 0.002561, "ask": 0.002565, "bid": 0.002557}, "HYDRA/USDT": {"last": 1.574, "ask": 1.575, "bid": 1.569}, "PTR/USDT": {"last": 0.0012, "ask": 0.001239, "bid": 0.0012}, "STEP/USDT": {"last": 0.010671, "ask": 0.010902, "bid": 0.010663}, "MATTER/USDT": {"last": 0.04389, "ask": 0.04472, "bid": 0.04371}, "KCS/USDT": {"last": 7.546, "ask": 7.616, "bid": 7.535}, "LIKE/USDT": {"last": 0.003049, "ask": 0.003136, "bid": 0.003037}, "COMP/USDT": {"last": 34.705, "ask": 34.816, "bid": 34.729}, "BAL/USDT": {"last": 5.493714, "ask": 5.507663, "bid": 5.496595}, "KWENTA/USDT": {"last": 372.44, "ask": 372.47, "bid": 364.48}, "AQT/USDT": {"last": 0.9987, "ask": 0.9832, "bid": 0.9452}, "CATHEON/USDT": {"last": 0.000684, "ask": 0.000688, "bid": 0.000682}, "EFI/USDT": {"last": 0.05208, "ask": 0.05241, "bid": 0.0516}, "CNS/USDT": {"last": 4.104e-06, "ask": 4.124e-06, "bid": 4.099e-06}, "GALO/USDT": {"last": 0.3272, "ask": 0.3293, "bid": 0.3255}, "MOOV/USDT": {"last": 0.004072, "ask": 0.004072, "bid": 0.003961}, "RUNE/USDT": {"last": 1.1717, "ask": 1.1762, "bid": 1.1716}, "ITEM/USDT": {"last": 0.000265, "ask": 0.000291, "bid": 0.000269}, "SCLP/USDT": {"last": 0.1707, "ask": 0.1711, "bid": 0.1694}, "UNCLEMINE/USDT": {"last": 0.0004719, "ask": 0.000505, "bid": 0.0004749}, "RBC/USDT": {"last": 0.01468, "ask": 0.01479, "bid": 0.0146}, "ETC/USDT": {"last": 18.11, "ask": 18.11, "bid": 18.1}, "PAW/USDT": {"last": 7.213e-06, "ask": 7.215e-06, "bid": 7.128e-06}, "XCV/USDT": {"last": 0.004086, "ask": 0.004095, "bid": 0.004013}, "FMXEN/USDT": {"last": 6.4383e-09, "ask": 6.4384e-09, "bid": 6.2e-09}, "KISHU/USDT": {"last": 3.574e-10, "ask": 3.574e-10, "bid": 3.563e-10}, "LIEN/USDT": {"last": 0.4922, "ask": 0.4924, "bid": 0.4803}, "FCT2/USDT": {"last": 0.05324, "ask": 0.05347, "bid": 0.05302}, "PYR/USDT": {"last": 2.999, "ask": 3.004, "bid": 2.996}, "EXD/USDT": {"last": 0.2272, "ask": 0.228, "bid": 0.2269}, "KOY/USDT": {"last": 0.0035, "ask": 0.00349, "bid": 0.00344}, "MVX/USDT": {"last": 1.649, "ask": 1.649, "bid": 1.634}, "HYPES/USDT": {"last": 0.003637, "ask": 0.003766, "bid": 0.003615}, "PHL/USDT": {"last": 0.01147, "ask": 0.01153, "bid": 0.01125}, "BLANKV2/USDT": {"last": 0.06639, "ask": 0.06791, "bid": 0.06631}, "EVA/USDT": {"last": 0.0007042, "ask": 0.0007204, "bid": 0.0007029}, "FTP/USDT": {"last": 0.00071, "ask": 0.0007295, "bid": 0.0007002}, "BULL/USDT": {"last": 7.001e-08, "ask": 7.001e-08, "bid": 6.702e-08}, "KNC/USDT": {"last": 0.5953, "ask": 0.5975, "bid": 0.5955}, "GASDAO/USDT": {"last": 8.03e-07, "ask": 8.16e-07, "bid": 7.93e-07}, "BHO/USDT": {"last": 0.0004691, "ask": 0.0004747, "bid": 0.0004673}, "SAFEMARS/USDT": {"last": 8.93e-09, "ask": 9.17e-09, "bid": 8.45e-09}, "ALT/USDT": {"last": 0.05511, "ask": 0.056, "bid": 0.05517}, "NWC/USDT": {"last": 0.08338, "ask": 0.08218, "bid": 0.08033}, "VALUE/USDT": {"last": 0.1744, "ask": 0.1761, "bid": 0.1723}, "EQUILIBRIUM/USDT": {"last": 0.04596, "ask": 0.0461, "bid": 0.04555}, "TORG/USDT": {"last": 1.956e-07, "ask": 2.149e-07, "bid": 1.994e-07}, "LITHO/USDT": {"last": 0.0002651, "ask": 0.0002778, "bid": 0.0002651}, "BIT/USDT": {"last": 0.4781, "ask": 0.479, "bid": 0.4779}, "CPAY/USDT": {"last": 0.0004611, "ask": 0.0004612, "bid": 0.0004592}, "DHP/USDT": {"last": 0.002747, "ask": 0.002746, "bid": 0.002713}, "OXT/USDT": {"last": 0.068, "ask": 0.06819, "bid": 0.06795}, "BP/USDT": {"last": 0.005201, "ask": 0.005232, "bid": 0.005103}, "PERP/USDT": {"last": 0.6136, "ask": 0.6152, "bid": 0.6134}, "STX/USDT": {"last": 0.6286, "ask": 0.6285, "bid": 0.628}, "ZIG/USDT": {"last": 0.005344, "ask": 0.005421, "bid": 0.005263}, "ANML/USDT": {"last": 0.0002819, "ask": 0.0002884, "bid": 0.0002814}, "PRMX/USDT": {"last": 8.4e-05, "ask": 8.5e-05, "bid": 8.3e-05}, "FOUR/USDT": {"last": 1.2e-05, "ask": 1.2e-05, "bid": 1.17e-05}, "MIM/USDT": {"last": 0.5576, "ask": 0.5497, "bid": 0.5128}, "BFC/USDT": {"last": 0.05091, "ask": 0.05152, "bid": 0.05065}, "ARK/USDT": {"last": 0.2707, "ask": 0.2713, "bid": 0.27}, "RAE/USDT": {"last": 1.1103, "ask": 1.1201, "bid": 1.1008}, "CERE/USDT": {"last": 0.004464, "ask": 0.004487, "bid": 0.00443}, "RVLT/USDT": {"last": 3.721e-08, "ask": 3.721e-08, "bid": 3.714e-08}, "DVC/USDT": {"last": 1.5673e-05, "ask": 1.5674e-05, "bid": 1.5673e-05}, "SEA/USDT": {"last": 0.003099, "ask": 0.003175, "bid": 0.003099}, "MKR/USDT": {"last": 635.2, "ask": 636.8, "bid": 635.5}, "GCAKE/USDT": {"last": 4.337e-07, "ask": 4.399e-07, "bid": 4.23e-07}, "MV/USDT": {"last": 0.1277, "ask": 0.1279, "bid": 0.1256}, "MIRL/USDT": {"last": 0.000701, "ask": 0.000722, "bid": 0.000697}, "MESH/USDT": {"last": 0.041, "ask": 0.04098, "bid": 0.03571}, "KLV/USDT": {"last": 0.003943, "ask": 0.00403, "bid": 0.003938}, "LBL/USDT": {"last": 0.003315, "ask": 0.003317, "bid": 0.003313}, "PZP/USDT": {"last": 0.06208, "ask": 0.06236, "bid": 0.06172}, "STEPWATCH/USDT": {"last": 0.001026, "ask": 0.001042, "bid": 0.001021}, "SCT/USDT": {"last": 0.13606, "ask": 0.14085, "bid": 0.136}, "AREA/USDT": {"last": 0.11534, "ask": 0.11595, "bid": 0.11537}, "RNDR/USDT": {"last": 1.774, "ask": 1.783, "bid": 1.768}, "JAM/USDT": {"last": 0.0003566, "ask": 0.0003652, "bid": 0.0003402}, "MATH/USDT": {"last": 0.09717, "ask": 0.09747, "bid": 0.09667}, "FER/USDT": {"last": 0.02264, "ask": 0.02306, "bid": 0.02262}, "MOM/USDT": {"last": 0.0693, "ask": 0.0696, "bid": 0.0692}, "Egoras Credit/USDT": {"last": 7.384, "ask": 7.537, "bid": 7.382}, "CPFC/USDT": {"last": 1.076, "ask": 1.104, "bid": 1.069}, "3AIR/USDT": {"last": 0.0061, "ask": 0.0061, "bid": 0.00604}, "PKR/USDT": {"last": 0.002203, "ask": 0.002196, "bid": 0.002195}, "ZRX/USDT": {"last": 0.2167, "ask": 0.217, "bid": 0.2164}, "BIOFI/USDT": {"last": 0.000845, "ask": 0.000846, "bid": 0.000842}, "ITSB/USDT": {"last": 0.002299, "ask": 0.002398, "bid": 0.00217}, "HSF/USDT": {"last": 0.5283, "ask": 0.5307, "bid": 0.5253}, "KMON/USDT": {"last": 0.00972, "ask": 0.00976, "bid": 0.00969}, "LUNR/USDT": {"last": 0.15955, "ask": 0.16297, "bid": 0.15823}, "XEP/USDT": {"last": 0.0002731, "ask": 0.0002739, "bid": 0.0002726}, "NBS/USDT": {"last": 0.0002076, "ask": 0.0002167, "bid": 0.0002058}, "SOLID/USDT": {"last": 0.3972, "ask": 0.4016, "bid": 0.3923}, "DEP/USDT": {"last": 0.002148, "ask": 0.002169, "bid": 0.002159}, "AUCTION/USDT": {"last": 4.944, "ask": 4.944, "bid": 4.918}, "WZM/USDT": {"last": 0.00948, "ask": 0.00948, "bid": 0.00909}, "CNTM/USDT": {"last": 0.001, "ask": 0.001019, "bid": 0.001001}, "BSCS/USDT": {"last": 0.010722, "ask": 0.010919, "bid": 0.010718}, "VAI/USDT": {"last": 0.06153, "ask": 0.06173, "bid": 0.06137}, "NULS/USDT": {"last": 0.2157, "ask": 0.2162, "bid": 0.2151}, "NEPT/USDT": {"last": 3.61e-05, "ask": 3.63e-05, "bid": 3.53e-05}, "BFT/USDT": {"last": 0.05317, "ask": 0.05324, "bid": 0.05262}, "VCF/USDT": {"last": 0.7164, "ask": 0.7204, "bid": 0.7076}, "XREATORS/USDT": {"last": 0.00872, "ask": 0.00886, "bid": 0.00868}, "FARA/USDT": {"last": 0.02836, "ask": 0.029, "bid": 0.02828}, "HOSKY/USDT": {"last": 1.915e-08, "ask": 1.929e-08, "bid": 1.877e-08}, "BUSD/USDT": {"last": 0.9997, "ask": 0.9998, "bid": 0.9997}, "ZURR/USDT": {"last": 6.802, "ask": 6.92, "bid": 6.756}, "REN/USDT": {"last": 0.07454, "ask": 0.07491, "bid": 0.07451}, "DG/USDT": {"last": 0.02247, "ask": 0.02247, "bid": 0.02213}, "MOVEZ/USDT": {"last": 0.001775, "ask": 0.001789, "bid": 0.001771}, "BLZ/USDT": {"last": 0.05873, "ask": 0.05891, "bid": 0.05872}, "HEGIC/USDT": {"last": 0.013857, "ask": 0.01387, "bid": 0.013806}, "EGAME/USDT": {"last": 6.539e-05, "ask": 6.564e-05, "bid": 6.342e-05}, "FOR/USDT": {"last": 0.01823, "ask": 0.01831, "bid": 0.01824}, "EURT/USDT": {"last": 1.0845, "ask": 1.0845, "bid": 1.0821}, "VKT/USDT": {"last": 0.000333, "ask": 0.000333, "bid": 0.000332}, "GOV/USDT": {"last": 0.00556, "ask": 0.005602, "bid": 0.005554}, "CBX/USDT": {"last": 0.02673, "ask": 0.02688, "bid": 0.02659}, "BAT/USDT": {"last": 0.2124, "ask": 0.2129, "bid": 0.212}, "SUZUME/USDT": {"last": 1.2159e-06, "ask": 1.2308e-06, "bid": 1.2135e-06}, "LIFE/USDT": {"last": 0.0002458, "ask": 0.0002463, "bid": 0.0002442}, "OCC/USDT": {"last": 0.1462, "ask": 0.149, "bid": 0.1462}, "KICKS/USDT": {"last": 0.001439, "ask": 0.00143, "bid": 0.001408}, "LVL/USDT": {"last": 4.629, "ask": 4.662, "bid": 4.618}, "KINE/USDT": {"last": 0.07899, "ask": 0.07921, "bid": 0.07889}, "COOK/USDT": {"last": 0.000237, "ask": 0.0002378, "bid": 0.0002314}, "BDT/USDT": {"last": 5.107e-05, "ask": 5.15e-05, "bid": 4.994e-05}, "LWD/USDT": {"last": 0.007999, "ask": 0.007996, "bid": 0.007563}, "KEK/USDT": {"last": 0.00028, "ask": 0.00027999, "bid": 0.00023189}, "XAUT/USDT": {"last": 2006.13, "ask": 2010.36, "bid": 2006.06}, "PLANETS/USDT": {"last": 0.001935, "ask": 0.001928, "bid": 0.001745}, "NIFTY/USDT": {"last": 0.000857, "ask": 0.000927, "bid": 0.000857}, "ANC/USDT": {"last": 0.00916, "ask": 0.00932, "bid": 0.0091}, "FREEDOM/USDT": {"last": 1.396e-07, "ask": 1.408e-07, "bid": 1.395e-07}, "OLEA/USDT": {"last": 0.487, "ask": 0.4873, "bid": 0.487}, "DEB/USDT": {"last": 0.005225, "ask": 0.005235, "bid": 0.005215}, "BEAM/USDT": {"last": 0.0348, "ask": 0.035, "bid": 0.03458}, "SMARS/USDT": {"last": 3.399e-09, "ask": 3.526e-09, "bid": 3.395e-09}, "CCD/USDT": {"last": 0.00706, "ask": 0.00707, "bid": 0.00706}, "GFLOKI/USDT": {"last": 8.3e-10, "ask": 8.4e-10, "bid": 8.3e-10}, "FND/USDT": {"last": 0.00293, "ask": 0.002957, "bid": 0.002906}, "MOON/USDT": {"last": 0.15822, "ask": 0.16199, "bid": 0.15667}, "FNCT/USDT": {"last": 0.001495, "ask": 0.001497, "bid": 0.001496}, "IGUP/USDT": {"last": 0.00868, "ask": 0.00869, "bid": 0.00858}, "SWG/USDT": {"last": 0.032257, "ask": 0.032301, "bid": 0.032251}, "XIDO/USDT": {"last": 2.01995, "ask": 2.0213, "bid": 1.93}, "POND/USDT": {"last": 0.008413, "ask": 0.008422, "bid": 0.008395}, "EDEN/USDT": {"last": 0.05355, "ask": 0.05563, "bid": 0.05332}, "PMG/USDT": {"last": 0.00047, "ask": 0.000528, "bid": 0.000471}, "LBC/USDT": {"last": 0.0094, "ask": 0.0098, "bid": 0.0094}, "UNFI/USDT": {"last": 4.1172, "ask": 4.1265, "bid": 4.1175}, "ATOLO/USDT": {"last": 0.00414, "ask": 0.004226, "bid": 0.003974}, "FORTH/USDT": {"last": 2.819, "ask": 2.829, "bid": 2.819}, "CIRUS/USDT": {"last": 0.05694, "ask": 0.05872, "bid": 0.05689}, "TYP/USDT": {"last": 1.66e-05, "ask": 1.71e-05, "bid": 1.66e-05}, "COVN/USDT": {"last": 0.219, "ask": 0.224, "bid": 0.216}, "RLC/USDT": {"last": 1.519, "ask": 1.519, "bid": 1.514}, "RON/USDT": {"last": 0.9473, "ask": 0.952, "bid": 0.9466}, "ITA/USDT": {"last": 1.3251, "ask": 1.3268, "bid": 1.3243}, "NEST/USDT": {"last": 0.013939, "ask": 0.014019, "bid": 0.0139}, "OBT/USDT": {"last": 0.04292, "ask": 0.04293, "bid": 0.04266}, "AUTO/USDT": {"last": 23.63, "ask": 23.9, "bid": 23.57}, "BLUES/USDT": {"last": 0.05276, "ask": 0.05317, "bid": 0.05289}, "USDJ/USDT": {"last": 1.1067, "ask": 1.108, "bid": 1.1019}, "ENTC/USDT": {"last": 8.5, "ask": 9.3457, "bid": 8.5001}, "NTN/USDT": {"last": 0.00279, "ask": 0.0028, "bid": 0.00276}, "CARE/USDT": {"last": 4e-05, "ask": 5e-05, "bid": 4e-05}, "MNG/USDT": {"last": 0.003239, "ask": 0.003238, "bid": 0.003179}, "PLA/USDT": {"last": 0.1805, "ask": 0.1805, "bid": 0.1799}, "CYS/USDT": {"last": 0.007923, "ask": 0.007936, "bid": 0.0078}, "VEMP/USDT": {"last": 0.01023, "ask": 0.01023, "bid": 0.01006}, "FITFI/USDT": {"last": 0.005866, "ask": 0.005904, "bid": 0.005859}, "OMC/USDT": {"last": 0.01787, "ask": 0.018368, "bid": 0.017821}, "CLEV/USDT": {"last": 11.113, "ask": 11.429, "bid": 11.056}, "DOGGY/USDT": {"last": 0.0003848, "ask": 0.0003909, "bid": 0.0003842}, "XRPC/USDT": {"last": 0.003159, "ask": 0.003159, "bid": 0.002878}, "MUTE/USDT": {"last": 0.5868, "ask": 0.5878, "bid": 0.5848}, "RAY/USDT": {"last": 0.1873, "ask": 0.1875, "bid": 0.1868}, "FOX/USDT": {"last": 0.02481, "ask": 0.02514, "bid": 0.02473}, "ETERNAL/USDT": {"last": 0.1497, "ask": 0.15, "bid": 0.1482}, "PRIMAL/USDT": {"last": 0.002486, "ask": 0.0025, "bid": 0.00247}, "LOVE/USDT": {"last": 0.12086, "ask": 0.12089, "bid": 0.12074}, "DEVT/USDT": {"last": 0.00314, "ask": 0.003165, "bid": 0.003124}, "FLEX/USDT": {"last": 2.551e-06, "ask": 2.647e-06, "bid": 2.551e-06}, "WE/USDT": {"last": 0.4632, "ask": 0.4764, "bid": 0.4578}, "LCT/USDT": {"last": 0.0052, "ask": 0.00521, "bid": 0.00517}, "STRM/USDT": {"last": 0.01228, "ask": 0.01229, "bid": 0.01221}, "PNG/USDT": {"last": 0.02991, "ask": 0.03005, "bid": 0.02985}, "PRARE/USDT": {"last": 0.004215, "ask": 0.004292, "bid": 0.0042}, "TOMO/USDT": {"last": 0.9476, "ask": 0.949, "bid": 0.9376}, "TDX/USDT": {"last": 0.0971, "ask": 0.0972, "bid": 0.0971}, "PLCU/USDT": {"last": 849.44, "ask": 854.99, "bid": 843.22}, "KABOSU/USDT": {"last": 1.78e-05, "ask": 1.795e-05, "bid": 1.777e-05}, "CASHZ/USDT": {"last": 0.0003652, "ask": 0.000378, "bid": 0.0003615}, "OKT/USDT": {"last": 16.76, "ask": 16.8, "bid": 16.73}, "SHARBI/USDT": {"last": 3.722e-06, "ask": 3.804e-06, "bid": 3.729e-06}, "FOOD/USDT": {"last": 0.097, "ask": 0.0976, "bid": 0.0921}, "EUL/USDT": {"last": 1.722, "ask": 1.778, "bid": 1.72}, "NAP/USDT": {"last": 3.678, "ask": 3.775, "bid": 3.678}, "ARBGPT/USDT": {"last": 0.0001568, "ask": 0.0001568, "bid": 0.0001529}, "ETHPAD/USDT": {"last": 0.00431, "ask": 0.0045, "bid": 0.00431}, "EMPIRE/USDT": {"last": 0.001084, "ask": 0.001083, "bid": 0.001079}, "WEFIN/USDT": {"last": 2.19e-05, "ask": 2.203e-05, "bid": 2.166e-05}, "AKRO/USDT": {"last": 0.003427, "ask": 0.003441, "bid": 0.003426}, "STA/USDT": {"last": 0.0254, "ask": 0.0278, "bid": 0.0256}, "UFEWO/USDT": {"last": 0.014757, "ask": 0.014955, "bid": 0.014686}, "WNCG/USDT": {"last": 0.0801, "ask": 0.08022, "bid": 0.08002}, "HTT/USDT": {"last": 0.000171, "ask": 0.000171, "bid": 0.0001704}, "CVP/USDT": {"last": 0.3718, "ask": 0.3726, "bid": 0.3714}, "T23/USDT": {"last": 3.5e-10, "ask": 3.6e-10, "bid": 3.5e-10}, "ZTG/USDT": {"last": 0.06271, "ask": 0.06376, "bid": 0.06269}, "BOO/USDT": {"last": 1.187, "ask": 1.206, "bid": 1.179}, "MAGIC/USDT": {"last": 0.8496, "ask": 0.8501, "bid": 0.8491}, "CUP/USDT": {"last": 0.0001056, "ask": 0.0001074, "bid": 0.0001052}, "MFET/USDT": {"last": 0.00205, "ask": 0.002082, "bid": 0.002046}, "SDL/USDT": {"last": 0.006032, "ask": 0.006623, "bid": 0.006041}, "METIS/USDT": {"last": 22.49, "ask": 22.52, "bid": 22.42}, "FEAR/USDT": {"last": 0.11113, "ask": 0.11248, "bid": 0.10966}, "ATC/USDT": {"last": 0.00039, "ask": 0.00039, "bid": 0.00038}, "KAVA/USDT": {"last": 0.9142, "ask": 0.9191, "bid": 0.9151}, "APN/USDT": {"last": 0.001218, "ask": 0.001242, "bid": 0.001214}, "CONV/USDT": {"last": 0.0008141, "ask": 0.000817, "bid": 0.0008061}, "POPCORN/USDT": {"last": 0.53, "ask": 0.54001, "bid": 0.50458}, "RNDX/USDT": {"last": 0.0001317, "ask": 0.0001315, "bid": 0.0001262}, "ARBI/USDT": {"last": 0.0014974, "ask": 0.0015239, "bid": 0.0015152}, "PHA/USDT": {"last": 0.115997, "ask": 0.116396, "bid": 0.116031}, "LSDS/USDT": {"last": 0.0812, "ask": 0.0976, "bid": 0.0786}, "ELF/USDT": {"last": 0.280533, "ask": 0.281522, "bid": 0.280942}, "NAS/USDT": {"last": 0.01096, "ask": 0.01111, "bid": 0.01093}, "VIDY/USDT": {"last": 4.342e-05, "ask": 4.453e-05, "bid": 4.325e-05}, "SAKAI/USDT": {"last": 6.8383, "ask": 6.923, "bid": 6.8223}, "WITCH/USDT": {"last": 0.134, "ask": 0.135, "bid": 0.134}, "JPEG/USDT": {"last": 0.0005326, "ask": 0.0005373, "bid": 0.0005301}, "ALICE/USDT": {"last": 1.2234, "ask": 1.2265, "bid": 1.2233}, "VOLTAGE/USDT": {"last": 0.000431, "ask": 0.000434, "bid": 0.0004277}, "TRVL/USDT": {"last": 0.03117, "ask": 0.03133, "bid": 0.0311}, "SQUAD/USDT": {"last": 0.00402, "ask": 0.0043, "bid": 0.00402}, "XCAD/USDT": {"last": 0.93683, "ask": 0.94753, "bid": 0.93577}, "LOOP/USDT": {"last": 0.07269, "ask": 0.07269, "bid": 0.07221}, "TFBX/USDT": {"last": 0.0002699, "ask": 0.0002743, "bid": 0.0002676}, "UBXS/USDT": {"last": 0.10531, "ask": 0.10531, "bid": 0.1053}, "OGGY/USDT": {"last": 1.059e-10, "ask": 1.08e-10, "bid": 1.061e-10}, "TAG/USDT": {"last": 0.3264, "ask": 0.3273, "bid": 0.321}, "IP3/USDT": {"last": 0.5928, "ask": 0.5944, "bid": 0.5881}, "RIN/USDT": {"last": 0.0938, "ask": 0.0956, "bid": 0.0916}, "IOST/USDT": {"last": 0.0092472, "ask": 0.009272, "bid": 0.0092469}, "IBAT/USDT": {"last": 0.000796, "ask": 0.0008, "bid": 0.000794}, "DZOO/USDT": {"last": 0.01231, "ask": 0.01231, "bid": 0.01222}, "PEEPO/USDT": {"last": 6.84e-08, "ask": 6.84e-08, "bid": 6.68e-08}, "GM/USDT": {"last": 1.1311e-05, "ask": 1.1385e-05, "bid": 1.1052e-05}, "SPA/USDT": {"last": 0.007846, "ask": 0.007886, "bid": 0.007811}, "BAJU/USDT": {"last": 0.06195, "ask": 0.06208, "bid": 0.0618}, "STARL/USDT": {"last": 1.278e-06, "ask": 1.285e-06, "bid": 1.278e-06}, "PARMA/USDT": {"last": 0.2573, "ask": 0.2588, "bid": 0.2538}, "RARE/USDT": {"last": 0.1007, "ask": 0.1011, "bid": 0.1007}, "TLM/USDT": {"last": 0.01496, "ask": 0.01499, "bid": 0.01496}, "MGG/USDT": {"last": 0.002704, "ask": 0.002771, "bid": 0.002682}, "COGE/USDT": {"last": 1.245e-08, "ask": 1.269e-08, "bid": 1.198e-08}, "RAK/USDT": {"last": 19.052, "ask": 19.745, "bid": 19.019}, "PSG/USDT": {"last": 4.725, "ask": 4.741, "bid": 4.719}, "XDB/USDT": {"last": 0.000837, "ask": 0.000853, "bid": 0.000821}, "FID/USDT": {"last": 0.002593, "ask": 0.002628, "bid": 0.002574}, "K21/USDT": {"last": 0.4839, "ask": 0.4887, "bid": 0.4826}, "NOOT/USDT": {"last": 7.22e-09, "ask": 7.3e-09, "bid": 7.15e-09}, "KTON/USDT": {"last": 6.9221, "ask": 7.0599, "bid": 6.8503}, "TARI/USDT": {"last": 1.4569, "ask": 1.5869, "bid": 1.3578}, "FRZSSCOIN/USDT": {"last": 0.000752, "ask": 0.000761, "bid": 0.000721}, "VEE/USDT": {"last": 0.0001099, "ask": 0.0001145, "bid": 0.0001091}, "FLX/USDT": {"last": 12.75, "ask": 12.8, "bid": 12.67}, "KOM/USDT": {"last": 0.0009871, "ask": 0.0009843, "bid": 0.0009839}, "HYVE/USDT": {"last": 0.06032, "ask": 0.06067, "bid": 0.06001}, "ALGB/USDT": {"last": 0.01345, "ask": 0.01357, "bid": 0.01333}, "DOGGO/USDT": {"last": 3.54e-09, "ask": 3.58e-09, "bid": 3.49e-09}, "PARAS/USDT": {"last": 0.01551, "ask": 0.01555, "bid": 0.0155}, "TNS/USDT": {"last": 0.002942, "ask": 0.003021, "bid": 0.002936}, "JEWEL/USDT": {"last": 0.1501, "ask": 0.1517, "bid": 0.1464}, "METAFI/USDT": {"last": 3.16, "ask": 3.176, "bid": 3.141}, "ORARE/USDT": {"last": 0.0427, "ask": 0.0432, "bid": 0.0419}, "YAY/USDT": {"last": 0.0008091, "ask": 0.0008108, "bid": 0.0008}, "POOLX/USDT": {"last": 2.882, "ask": 2.876, "bid": 2.852}, "MARSH/USDT": {"last": 0.1008, "ask": 0.10255, "bid": 0.10015}, "RDPX/USDT": {"last": 18.73, "ask": 18.75, "bid": 18.69}, "VGX/USDT": {"last": 0.1445, "ask": 0.1449, "bid": 0.1446}, "ARPA/USDT": {"last": 0.05438, "ask": 0.05477, "bid": 0.05471}, "CMP/USDT": {"last": 0.0387, "ask": 0.0389, "bid": 0.0382}, "THOL/USDT": {"last": 0.04753, "ask": 0.04528, "bid": 0.04504}, "VSTA/USDT": {"last": 0.2333, "ask": 0.2333, "bid": 0.2243}, "DRM/USDT": {"last": 0.005959, "ask": 0.005996, "bid": 0.005927}, "MIX/USDT": {"last": 0.002116, "ask": 0.00218, "bid": 0.002106}, "FNF/USDT": {"last": 8e-05, "ask": 8e-05, "bid": 7e-05}, "BEAR/USDT": {"last": 3.669e-08, "ask": 3.665e-08, "bid": 3.314e-08}, "SILK/USDT": {"last": 0.431, "ask": 0.435, "bid": 0.432}, "GARI/USDT": {"last": 0.05162, "ask": 0.05191, "bid": 0.05157}, "AOK/USDT": {"last": 0.0002136, "ask": 0.0002206, "bid": 0.000208}, "MMY/USDT": {"last": 3.629, "ask": 3.77, "bid": 3.629}, "QUINT/USDT": {"last": 1.09, "ask": 1.102, "bid": 1.078}, "KMA/USDT": {"last": 0.001743, "ask": 0.001743, "bid": 0.001736}, "CHAIN/USDT": {"last": 0.01242, "ask": 0.01273, "bid": 0.0123}, "IZI/USDT": {"last": 0.01669, "ask": 0.016852, "bid": 0.016516}, "IOEX/USDT": {"last": 0.006159, "ask": 0.00614, "bid": 0.005503}, "PINKSALE/USDT": {"last": 177.11, "ask": 178.05, "bid": 176.5}, "CTXC/USDT": {"last": 0.15372, "ask": 0.154, "bid": 0.15364}, "ORE/USDT": {"last": 0.003346, "ask": 0.003368, "bid": 0.003283}, "AFC/USDT": {"last": 1.546, "ask": 1.586, "bid": 1.539}, "XMX/USDT": {"last": 1.0166e-05, "ask": 1.0414e-05, "bid": 9.909e-06}, "LUNCH/USDT": {"last": 0.000121, "ask": 0.0001251, "bid": 0.0001182}, "CWEB/USDT": {"last": 0.02728, "ask": 0.02719, "bid": 0.02704}, "UNI/USDT": {"last": 5.1356, "ask": 5.1371, "bid": 5.1367}, "OWL/USDT": {"last": 0.00668, "ask": 0.00668, "bid": 0.00667}, "UT/USDT": {"last": 0.0007757, "ask": 0.0007782, "bid": 0.0007751}, "PAT/USDT": {"last": 1.12e-05, "ask": 1.18e-05, "bid": 1.12e-05}, "WMT/USDT": {"last": 0.1385, "ask": 0.1386, "bid": 0.1384}, "DRF/USDT": {"last": 0.000983, "ask": 0.0009866, "bid": 0.00096}, "AGI/USDT": {"last": 0.1006, "ask": 0.10061, "bid": 0.1006}, "ROCKI/USDT": {"last": 0.01619, "ask": 0.01667, "bid": 0.01605}, "TROVE/USDT": {"last": 0.01998, "ask": 0.02017, "bid": 0.01996}, "BBF/USDT": {"last": 0.2401, "ask": 0.2385, "bid": 0.2303}, "QRDO/USDT": {"last": 0.1033, "ask": 0.1033, "bid": 0.1029}, "KAS/USDT": {"last": 0.020898, "ask": 0.020898, "bid": 0.020851}, "UNB/USDT": {"last": 0.000852, "ask": 0.0008548, "bid": 0.00084}, "FBX/USDT": {"last": 0.01253, "ask": 0.0124, "bid": 0.01171}, "SANDWICH/USDT": {"last": 0.000901, "ask": 0.000901, "bid": 0.000871}, "OMNOM/USDT": {"last": 1.042e-09, "ask": 1.047e-09, "bid": 1.029e-09}, "XYM/USDT": {"last": 0.02919, "ask": 0.0294, "bid": 0.0291}, "CREO/USDT": {"last": 0.002802, "ask": 0.002825, "bid": 0.002797}, "SSV/USDT": {"last": 20.635, "ask": 20.62, "bid": 20.575}, "MAF/USDT": {"last": 0.1215, "ask": 0.1217, "bid": 0.1211}, "DTR/USDT": {"last": 0.8859, "ask": 0.8888, "bid": 0.8858}, "PHB/USDT": {"last": 0.6513, "ask": 0.6526, "bid": 0.6509}, "BLT/USDT": {"last": 0.02433, "ask": 0.02478, "bid": 0.02418}, "FUTURE/USDT": {"last": 0.1872, "ask": 0.2291, "bid": 0.1872}, "ATOZ/USDT": {"last": 0.13132, "ask": 0.13407, "bid": 0.12485}, "OBROK/USDT": {"last": 1.1739e-09, "ask": 1.1917e-09, "bid": 1.174e-09}, "FPFT/USDT": {"last": 0.01216, "ask": 0.01297, "bid": 0.01216}, "DIE/USDT": {"last": 5.323e-08, "ask": 5.339e-08, "bid": 5.3e-08}, "BRS/USDT": {"last": 0.0001483, "ask": 0.0001502, "bid": 0.000148}, "FEVR/USDT": {"last": 0.0006238, "ask": 0.0006241, "bid": 0.000624}, "MBL/USDT": {"last": 0.00281, "ask": 0.002817, "bid": 0.002808}, "VIM/USDT": {"last": 0.00495, "ask": 0.00492, "bid": 0.00461}, "PCR/USDT": {"last": 0.000505, "ask": 0.000505, "bid": 0.0005024}, "NRV/USDT": {"last": 0.004697, "ask": 0.004859, "bid": 0.004696}, "KIN/USDT": {"last": 7.795e-06, "ask": 7.85e-06, "bid": 7.697e-06}, "DUX/USDT": {"last": 0.01028, "ask": 0.01044, "bid": 0.0103}, "NXDT/USDT": {"last": 0.003784, "ask": 0.00379, "bid": 0.003769}, "WALV/USDT": {"last": 0.03489, "ask": 0.0354, "bid": 0.03484}, "ATNT/USDT": {"last": 0.002735, "ask": 0.002857, "bid": 0.002629}, "CVNT/USDT": {"last": 0.515, "ask": 0.536, "bid": 0.506}, "AM/USDT": {"last": 1.2207, "ask": 1.2444, "bid": 1.2116}, "DOSE/USDT": {"last": 0.004761, "ask": 0.004777, "bid": 0.004713}, "MDX/USDT": {"last": 0.06341, "ask": 0.06452, "bid": 0.06298}, "GRAIL/USDT": {"last": 1544.53, "ask": 1554.72, "bid": 1540.36}, "NPICK/USDT": {"last": 0.0002212, "ask": 0.0002744, "bid": 0.0002313}, "ARTI/USDT": {"last": 0.00823, "ask": 0.00837, "bid": 0.00783}, "POLYDOGE/USDT": {"last": 5.755e-09, "ask": 5.758e-09, "bid": 5.73e-09}, "ALIEN/USDT": {"last": 0.0547, "ask": 0.0589, "bid": 0.0555}, "PEPA/USDT": {"last": 1.543e-11, "ask": 1.544e-11, "bid": 1.539e-11}, "MBS/USDT": {"last": 0.0428, "ask": 0.04311, "bid": 0.04247}, "CRP/USDT": {"last": 0.003254, "ask": 0.003328, "bid": 0.003246}, "RPG/USDT": {"last": 0.819, "ask": 0.822, "bid": 0.815}, "EWC/USDT": {"last": 0.0971, "ask": 0.0972, "bid": 0.0966}, "YFI/USDT": {"last": 6861.88784, "ask": 6889.1962, "bid": 6873.22207}, "DASH/USDT": {"last": 40.22, "ask": 40.3, "bid": 40.2}, "APT1/USDT": {"last": 1.789, "ask": 1.79, "bid": 1.787}, "INSUR/USDT": {"last": 0.07129, "ask": 0.07138, "bid": 0.07061}, "OOKI/USDT": {"last": 0.003078, "ask": 0.00308, "bid": 0.00306}, "FWW/USDT": {"last": 1.1001e-06, "ask": 1.1001e-06, "bid": 1.1e-06}, "JGN/USDT": {"last": 0.02473, "ask": 0.02504, "bid": 0.02463}, "MMIT/USDT": {"last": 4.286e-07, "ask": 4.304e-07, "bid": 4.274e-07}, "AVG/USDT": {"last": 0.04198, "ask": 0.04201, "bid": 0.04135}, "GDC/USDT": {"last": 0.0002345, "ask": 0.0002355, "bid": 0.0002344}, "METAX/USDT": {"last": 0.059, "ask": 0.05898, "bid": 0.0584}, "WOMBAT/USDT": {"last": 0.002555, "ask": 0.002558, "bid": 0.002554}, "GFX/USDT": {"last": 0.04373, "ask": 0.04351, "bid": 0.03286}, "NUX/USDT": {"last": 0.008189, "ask": 0.008198, "bid": 0.00818}, "IQ/USDT": {"last": 0.005102, "ask": 0.005127, "bid": 0.005112}, "COREUM/USDT": {"last": 0.2232, "ask": 0.2236, "bid": 0.2228}, "ZOON/USDT": {"last": 0.0006133, "ask": 0.0006244, "bid": 0.0006082}, "MTRG/USDT": {"last": 2.268, "ask": 2.284, "bid": 2.257}, "LNR/USDT": {"last": 0.01598, "ask": 0.01598, "bid": 0.01563}, "TCT/USDT": {"last": 0.001068, "ask": 0.001087, "bid": 0.001066}, "YFII/USDT": {"last": 919.7026, "ask": 921.8071, "bid": 920.0818}, "GAIA/USDT": {"last": 0.00312, "ask": 0.003226, "bid": 0.003113}, "COMBO/USDT": {"last": 0.0303, "ask": 0.03083, "bid": 0.03029}, "AXS/USDT": {"last": 6.716, "ask": 6.742, "bid": 6.723}, "CTN/USDT": {"last": 0.5502, "ask": 0.5634, "bid": 0.5503}, "NFTY/USDT": {"last": 0.002251, "ask": 0.002266, "bid": 0.002238}, "FIO/USDT": {"last": 0.02704, "ask": 0.02707, "bid": 0.027}, "LIT/USDT": {"last": 0.804, "ask": 0.805, "bid": 0.8028}, "TITAN/USDT": {"last": 3.984e-08, "ask": 4.004e-08, "bid": 3.901e-08}, "MONG/USDT": {"last": 6.9997e-08, "ask": 7e-08, "bid": 6.9999e-08}, "ELON/USDT": {"last": 2.131e-07, "ask": 2.132e-07, "bid": 2.119e-07}, "EXFI/USDT": {"last": 0.1992, "ask": 0.2012, "bid": 0.1972}, "WOPT/USDT": {"last": 0.01871, "ask": 0.01875, "bid": 0.01834}, "EVER/USDT": {"last": 0.03911, "ask": 0.03946, "bid": 0.03871}, "DEFIT/USDT": {"last": 0.0668, "ask": 0.0655, "bid": 0.0605}, "TABOO/USDT": {"last": 0.00348, "ask": 0.003587, "bid": 0.003447}, "BANANA/USDT": {"last": 0.02517, "ask": 0.02526, "bid": 0.02513}, "KASTA/USDT": {"last": 0.01756, "ask": 0.01799, "bid": 0.01751}, "KBD/USDT": {"last": 0.00171, "ask": 0.001742, "bid": 0.001611}, "MNFT/USDT": {"last": 2.125e-05, "ask": 2.135e-05, "bid": 2.109e-05}, "SFT/USDT": {"last": 0.705, "ask": 0.7199, "bid": 0.697}, "SOS/USDT": {"last": 6.488e-08, "ask": 6.55e-08, "bid": 6.467e-08}, "AIE/USDT": {"last": 0.005226, "ask": 0.0067, "bid": 0.00523}, "HELLO/USDT": {"last": 0.05622, "ask": 0.05683, "bid": 0.05595}, "ARMOR/USDT": {"last": 0.004346, "ask": 0.004369, "bid": 0.00432}, "KONO/USDT": {"last": 0.02273, "ask": 0.02278, "bid": 0.02267}, "RITE/USDT": {"last": 0.00275, "ask": 0.002755, "bid": 0.002735}, "GENE/USDT": {"last": 0.4704, "ask": 0.4797, "bid": 0.4632}, "MMUI/USDT": {"last": 0.1083, "ask": 0.1133, "bid": 0.1084}, "HNB/USDT": {"last": 0.01243, "ask": 0.01259, "bid": 0.01232}, "KPC/USDT": {"last": 0.00498, "ask": 0.00498, "bid": 0.00458}, "X1/USDT": {"last": 1.5, "ask": 1.5984, "bid": 1.4821}, "LOFI/USDT": {"last": 0.00598, "ask": 0.00617, "bid": 0.00598}, "VICS/USDT": {"last": 0.074, "ask": 0.07464, "bid": 0.07301}, "SHIBA/USDT": {"last": 6.09e-09, "ask": 6.08e-09, "bid": 5.95e-09}, "ZIX/USDT": {"last": 0.0008475, "ask": 0.0008475, "bid": 0.0008474}, "SPGBB/USDT": {"last": 1.655e-05, "ask": 1.677e-05, "bid": 1.62e-05}, "MELOS/USDT": {"last": 0.005687, "ask": 0.0057, "bid": 0.005638}, "STOS/USDT": {"last": 0.4993, "ask": 0.5012, "bid": 0.4961}, "DPX/USDT": {"last": 125.79, "ask": 129.04, "bid": 125.36}, "MVL/USDT": {"last": 0.003292, "ask": 0.003334, "bid": 0.003249}, "IMPT/USDT": {"last": 0.007, "ask": 0.00747, "bid": 0.00686}, "PIAS/USDT": {"last": 0.00042, "ask": 0.00042, "bid": 0.00041}, "BONDLYV2/USDT": {"last": 0.005285, "ask": 0.005363, "bid": 0.005333}, "SAUCE/USDT": {"last": 0.01539, "ask": 0.01568, "bid": 0.01544}, "KOSON/USDT": {"last": 0.02026, "ask": 0.02027, "bid": 0.02026}, "MANA/USDT": {"last": 0.4511, "ask": 0.4516, "bid": 0.4513}, "YDF/USDT": {"last": 0.00597, "ask": 0.00597, "bid": 0.00594}, "OKB/USDT": {"last": 44.614, "ask": 44.715, "bid": 44.611}, "KDG/USDT": {"last": 0.000644, "ask": 0.000657, "bid": 0.000634}, "GFAL/USDT": {"last": 0.008849, "ask": 0.008849, "bid": 0.008837}, "WDOGE/USDT": {"last": 0.07168, "ask": 0.07216, "bid": 0.07185}, "INVI/USDT": {"last": 1.371, "ask": 1.4, "bid": 1.275}, "ASTO/USDT": {"last": 0.03015, "ask": 0.03027, "bid": 0.03006}, "AMA/USDT": {"last": 0.00539, "ask": 0.00548, "bid": 0.00527}, "ADS/USDT": {"last": 0.1148, "ask": 0.11487, "bid": 0.11237}, "QKC/USDT": {"last": 0.009222, "ask": 0.009309, "bid": 0.00919}, "STORJ/USDT": {"last": 0.3022, "ask": 0.303, "bid": 0.3022}, "SMILE/USDT": {"last": 2.442e-05, "ask": 2.464e-05, "bid": 2.438e-05}, "EG/USDT": {"last": 0.0005354, "ask": 0.0005381, "bid": 0.0005336}, "TOMI/USDT": {"last": 3.9539, "ask": 3.9706, "bid": 3.9515}, "RUG/USDT": {"last": 2.28e-06, "ask": 2.43e-06, "bid": 2.15e-06}, "LOVELY/USDT": {"last": 5.441e-08, "ask": 5.507e-08, "bid": 5.425e-08}, "SAT/USDT": {"last": 0.0033, "ask": 0.003405, "bid": 0.003301}, "PWAR/USDT": {"last": 0.003966, "ask": 0.004053, "bid": 0.003966}, "IOTX/USDT": {"last": 0.021338, "ask": 0.021411, "bid": 0.021337}, "IXT/USDT": {"last": 0.4128, "ask": 0.4131, "bid": 0.4125}, "CVX/USDT": {"last": 4.483, "ask": 4.489, "bid": 4.477}, "SNFT/USDT": {"last": 0.05043, "ask": 0.05105, "bid": 0.0501}, "PSTAKE/USDT": {"last": 0.04887, "ask": 0.04908, "bid": 0.0487}, "FILDA/USDT": {"last": 0.001269, "ask": 0.001292, "bid": 0.001266}, "BORING/USDT": {"last": 0.002865, "ask": 0.00289, "bid": 0.002849}, "QVI/USDT": {"last": 0.0846, "ask": 0.0861, "bid": 0.0808}, "WNXM/USDT": {"last": 26.2475, "ask": 26.2925, "bid": 26.2203}, "XET/USDT": {"last": 0.000585, "ask": 0.000608, "bid": 0.00059}, "STORE/USDT": {"last": 0.02655, "ask": 0.02671, "bid": 0.02619}, "SFM/USDT": {"last": 0.0001893, "ask": 0.0001904, "bid": 0.0001809}, "SON/USDT": {"last": 0.0002889, "ask": 0.0002932, "bid": 0.0002886}, "STETH/USDT": {"last": 1763.41, "ask": 1796.44, "bid": 1756.03}, "MAV/USDT": {"last": 1.6, "ask": 1.7795, "bid": 1.6419}, "PEN/USDT": {"last": 0.0459, "ask": 0.04632, "bid": 0.0456}, "LEMC/USDT": {"last": 0.0027, "ask": 0.00273, "bid": 0.00267}, "CAPO/USDT": {"last": 0.00865, "ask": 0.00866, "bid": 0.00858}, "ALPACA/USDT": {"last": 0.2068, "ask": 0.2078, "bid": 0.207}, "REELT/USDT": {"last": 0.01539, "ask": 0.0146, "bid": 0.01352}, "HIVE/USDT": {"last": 0.359, "ask": 0.3599, "bid": 0.3588}, "KP3R/USDT": {"last": 63.45, "ask": 63.66, "bid": 63.44}, "METAL/USDT": {"last": 0.07903, "ask": 0.08237, "bid": 0.07952}, "WAIT/USDT": {"last": 0.2883, "ask": 0.2952, "bid": 0.2818}, "STAT/USDT": {"last": 0.1056, "ask": 0.1063, "bid": 0.1042}, "LSD/USDT": {"last": 0.01448, "ask": 0.01482, "bid": 0.01446}, "ANKR/USDT": {"last": 0.0250763, "ask": 0.0251807, "bid": 0.0251136}, "TRAVA/USDT": {"last": 0.0004175, "ask": 0.0004196, "bid": 0.0004129}, "SERO/USDT": {"last": 0.01199, "ask": 0.01245, "bid": 0.01182}, "RSS3/USDT": {"last": 0.1086, "ask": 0.1086, "bid": 0.1083}, "BEND/USDT": {"last": 0.006612, "ask": 0.006757, "bid": 0.006609}, "NEBL/USDT": {"last": 0.04589, "ask": 0.0459, "bid": 0.04588}, "ORN/USDT": {"last": 1.0804, "ask": 1.0816, "bid": 1.0814}, "FANC/USDT": {"last": 0.0416, "ask": 0.0418, "bid": 0.0414}, "NATION/USDT": {"last": 364.88, "ask": 365.82, "bid": 363.68}, "VITA/USDT": {"last": 1.64, "ask": 1.642, "bid": 1.608}, "ZAM/USDT": {"last": 0.0043, "ask": 0.004315, "bid": 0.004264}, "BADGER/USDT": {"last": 2.546, "ask": 2.549, "bid": 2.544}, "VELODROME/USDT": {"last": 0.08493, "ask": 0.086, "bid": 0.08502}, "GENE1/USDT": {"last": 0.004249, "ask": 0.004409, "bid": 0.004224}, "ACX/USDT": {"last": 0.04408, "ask": 0.04433, "bid": 0.0435}, "LEOX/USDT": {"last": 0.3074, "ask": 0.3078, "bid": 0.3069}, "BAKE/USDT": {"last": 0.1468, "ask": 0.1473, "bid": 0.1469}, "NAX/USDT": {"last": 7.976e-05, "ask": 8.109e-05, "bid": 7.92e-05}, "SNT/USDT": {"last": 0.0238721, "ask": 0.0240834, "bid": 0.0238561}, "BUP/USDT": {"last": 0.01052, "ask": 0.01052, "bid": 0.01048}, "ACM/USDT": {"last": 2.3, "ask": 2.313, "bid": 2.304}, "DEXTF/USDT": {"last": 0.056, "ask": 0.05639, "bid": 0.056}, "NORD/USDT": {"last": 0.1231, "ask": 0.1232, "bid": 0.1212}, "JOY/USDT": {"last": 0.07185, "ask": 0.07378, "bid": 0.07191}, "BOSON/USDT": {"last": 0.1717, "ask": 0.1733, "bid": 0.1712}, "FO/USDT": {"last": 0.0008503, "ask": 0.00093, "bid": 0.0008503}, "MCONTENT/USDT": {"last": 9.75e-10, "ask": 9.81e-10, "bid": 9.45e-10}, "OMG/USDT": {"last": 0.77425, "ask": 0.77704, "bid": 0.77326}, "MPH/USDT": {"last": 1.922, "ask": 1.961, "bid": 1.916}, "NZERO/USDT": {"last": 0.0248, "ask": 0.0254, "bid": 0.0244}, "DOP/USDT": {"last": 0.6143, "ask": 0.6143, "bid": 0.604}, "NEXA/USDT": {"last": 1.238e-05, "ask": 1.242e-05, "bid": 1.238e-05}, "HZN/USDT": {"last": 0.03849, "ask": 0.03852, "bid": 0.03841}, "RUN5KM/USDT": {"last": 9.6e-05, "ask": 9.89e-05, "bid": 9.17e-05}, "RPL/USDT": {"last": 45.87, "ask": 46.02, "bid": 45.84}, "INTER/USDT": {"last": 2.707, "ask": 2.72, "bid": 2.701}, "ZEN/USDT": {"last": 8.188, "ask": 8.226, "bid": 8.196}, "MCB/USDT": {"last": 11.723, "ask": 11.924, "bid": 11.66}, "GTCOIN/USDT": {"last": 0.01733, "ask": 0.01736, "bid": 0.01732}, "SC/USDT": {"last": 0.00337, "ask": 0.003371, "bid": 0.003352}, "GUM/USDT": {"last": 0.01206, "ask": 0.01219, "bid": 0.01195}, "ARA/USDT": {"last": 0.000686, "ask": 0.000713, "bid": 0.0007001}, "DORA/USDT": {"last": 2.428, "ask": 2.434, "bid": 2.414}, "HIBS/USDT": {"last": 0.000133, "ask": 0.0001367, "bid": 0.0001323}, "DV/USDT": {"last": 0.0017063, "ask": 0.0017466, "bid": 0.0016803}, "CRAFT/USDT": {"last": 0.005336, "ask": 0.005485, "bid": 0.005336}, "REEF/USDT": {"last": 0.002164, "ask": 0.002173, "bid": 0.002161}, "MYRIA/USDT": {"last": 0.003111, "ask": 0.003122, "bid": 0.003103}, "MCT/USDT": {"last": 0.000803, "ask": 0.000809, "bid": 0.000784}, "GOLDFINCH/USDT": {"last": 0.4215, "ask": 0.4238, "bid": 0.4221}, "BEYOND/USDT": {"last": 0.002165, "ask": 0.002208, "bid": 0.002165}, "NYM/USDT": {"last": 0.172, "ask": 0.1738, "bid": 0.1711}, "PTP/USDT": {"last": 0.04381, "ask": 0.04416, "bid": 0.04328}, "CLS/USDT": {"last": 0.05491, "ask": 0.05524, "bid": 0.05456}, "CKB/USDT": {"last": 0.003088, "ask": 0.003112, "bid": 0.003096}, "CRU/USDT": {"last": 0.8305, "ask": 0.854, "bid": 0.8257}, "SUI/USDT": {"last": 1.0921, "ask": 1.0918, "bid": 1.0909}, "GMEE/USDT": {"last": 0.010055, "ask": 0.010113, "bid": 0.010012}, "STEEM/USDT": {"last": 0.1935, "ask": 0.1945, "bid": 0.1923}, "BSW/USDT": {"last": 0.1268, "ask": 0.127, "bid": 0.1265}, "YARD/USDT": {"last": 0.0001461, "ask": 0.0001465, "bid": 0.0001453}, "METAHERO/USDT": {"last": 0.0032, "ask": 0.003231, "bid": 0.0032}, "FLOKICEO/USDT": {"last": 2.499e-11, "ask": 2.493e-11, "bid": 2.462e-11}, "TAO/USDT": {"last": 33.97, "ask": 33.98, "bid": 33.97}, "ETHA/USDT": {"last": 0.01752, "ask": 0.01754, "bid": 0.01732}, "ALPA/USDT": {"last": 0.02297, "ask": 0.02318, "bid": 0.02292}, "SWAP/USDT": {"last": 0.23788, "ask": 0.23717, "bid": 0.23343}, "ZINU/USDT": {"last": 0.000868, "ask": 0.000883, "bid": 0.000852}, "3KM/USDT": {"last": 0.0301, "ask": 0.0302, "bid": 0.0299}, "JONES/USDT": {"last": 1.516, "ask": 1.522, "bid": 1.489}, "GODS/USDT": {"last": 0.17, "ask": 0.1705, "bid": 0.1699}, "BTCBAM/USDT": {"last": 1.098, "ask": 1.098, "bid": 1.0901}, "DYP/USDT": {"last": 0.06121, "ask": 0.06241, "bid": 0.06124}, "AIBB/USDT": {"last": 1.327e-09, "ask": 1.337e-09, "bid": 1.311e-09}, "SAITAMA/USDT": {"last": 0.0009699, "ask": 0.0009712, "bid": 0.0009645}, "CLIPS/USDT": {"last": 5.543e-06, "ask": 5.54e-06, "bid": 5.422e-06}, "B20/USDT": {"last": 0.09582, "ask": 0.09736, "bid": 0.09531}, "THALES/USDT": {"last": 0.462, "ask": 0.4633, "bid": 0.4586}, "MCHC/USDT": {"last": 0.07844, "ask": 0.07903, "bid": 0.07784}, "FAYRE/USDT": {"last": 0.00051, "ask": 0.000508, "bid": 0.000506}, "BSCPAD/USDT": {"last": 0.13, "ask": 0.1319, "bid": 0.1309}, "PROS1/USDT": {"last": 0.01042, "ask": 0.01045, "bid": 0.01035}, "NHT/USDT": {"last": 0.0002797, "ask": 0.0002822, "bid": 0.000276}, "BNT/USDT": {"last": 0.4189, "ask": 0.4198, "bid": 0.4181}, "LBTC/USDT": {"last": 0.26046, "ask": 0.27478, "bid": 0.26044}, "RSR/USDT": {"last": 0.002793, "ask": 0.002793, "bid": 0.002786}, "RAB/USDT": {"last": 0.007463, "ask": 0.007479, "bid": 0.007421}, "WAXP/USDT": {"last": 0.05569, "ask": 0.05569, "bid": 0.05515}, "LFG/USDT": {"last": 0.000882, "ask": 0.000913, "bid": 0.000894}, "WTR/USDT": {"last": 0.0153, "ask": 0.01535, "bid": 0.01526}, "GPT/USDT": {"last": 0.022521, "ask": 0.02266, "bid": 0.02254}, "BCG/USDT": {"last": 0.000349, "ask": 0.000358, "bid": 0.000344}, "REF/USDT": {"last": 0.10161, "ask": 0.10395, "bid": 0.1015}, "RJV/USDT": {"last": 0.02592, "ask": 0.0268, "bid": 0.02583}, "ONSTON/USDT": {"last": 0.004166, "ask": 0.004195, "bid": 0.004143}, "NAOS/USDT": {"last": 0.01695, "ask": 0.01695, "bid": 0.01609}, "MOOI/USDT": {"last": 0.1386, "ask": 0.139, "bid": 0.1377}, "DOGEKING/USDT": {"last": 4.5e-09, "ask": 4.5e-09, "bid": 4.249e-09}, "TIDAL/USDT": {"last": 0.0002057, "ask": 0.0002092, "bid": 0.0002054}, "NOM/USDT": {"last": 0.448, "ask": 0.452, "bid": 0.449}, "GOLD/USDT": {"last": 0.005274, "ask": 0.005317, "bid": 0.005194}, "TOK/USDT": {"last": 0.001155, "ask": 0.001311, "bid": 0.001155}, "SYS/USDT": {"last": 0.1183, "ask": 0.1183, "bid": 0.1179}, "EOSC/USDT": {"last": 0.00163, "ask": 0.001643, "bid": 0.0016}, "ZYRO/USDT": {"last": 0.005726, "ask": 0.005758, "bid": 0.005721}, "ADP/USDT": {"last": 0.003362, "ask": 0.003393, "bid": 0.003294}, "ASS/USDT": {"last": 5.615e-10, "ask": 6.087e-10, "bid": 5.617e-10}, "IDYP/USDT": {"last": 0.000988, "ask": 0.001003, "bid": 0.000993}, "SAK/USDT": {"last": 0.001747, "ask": 0.00175, "bid": 0.00174}, "BST/USDT": {"last": 0.2547, "ask": 0.2548, "bid": 0.2545}, "DRAC/USDT": {"last": 0.004016, "ask": 0.003977, "bid": 0.003624}, "TOKKI/USDT": {"last": 0.01539, "ask": 0.01626, "bid": 0.01536}, "REVV/USDT": {"last": 0.008973, "ask": 0.008995, "bid": 0.008948}, "DEGEN/USDT": {"last": 2.999e-07, "ask": 3.036e-07, "bid": 2.989e-07}, "XX/USDT": {"last": 0.1488, "ask": 0.1488, "bid": 0.1474}, "CETUS/USDT": {"last": 0.1148, "ask": 0.115, "bid": 0.1145}, "RAIN/USDT": {"last": 0.001045, "ask": 0.001067, "bid": 0.001047}, "AGILITY/USDT": {"last": 0.02042, "ask": 0.02121, "bid": 0.02016}, "DIONE/USDT": {"last": 0.00285, "ask": 0.0028944, "bid": 0.0028501}, "GHD/USDT": {"last": 1.5e-05, "ask": 1.501e-05, "bid": 1.5e-05}, "PIT/USDT": {"last": 4.255e-10, "ask": 4.265e-10, "bid": 4.248e-10}, "XSPECTAR/USDT": {"last": 0.06243, "ask": 0.06157, "bid": 0.05643}, "ODDZ/USDT": {"last": 0.01384, "ask": 0.01388, "bid": 0.01369}, "TKO/USDT": {"last": 0.2766, "ask": 0.2774, "bid": 0.2767}, "BTM/USDT": {"last": 0.019832, "ask": 0.019961, "bid": 0.019506}, "DXL/USDT": {"last": 0.00529, "ask": 0.00529, "bid": 0.005173}, "NUDES/USDT": {"last": 3.411e-10, "ask": 3.547e-10, "bid": 3.411e-10}, "LBA/USDT": {"last": 0.0003134, "ask": 0.0003063, "bid": 0.0002888}, "CNTR/USDT": {"last": 6.08e-05, "ask": 6.09e-05, "bid": 5.81e-05}, "BAMBOO/USDT": {"last": 0.021944, "ask": 0.022168, "bid": 0.021744}, "ARV/USDT": {"last": 4.621e-05, "ask": 4.618e-05, "bid": 4.573e-05}, "APE/USDT": {"last": 3.273, "ask": 3.277, "bid": 3.272}, "LADYS/USDT": {"last": 5.543e-08, "ask": 5.543e-08, "bid": 5.538e-08}, "FIDA/USDT": {"last": 0.3359, "ask": 0.3359, "bid": 0.3338}, "ZBC/USDT": {"last": 0.01473, "ask": 0.01473, "bid": 0.0146}, "UGAS/USDT": {"last": 0.000843, "ask": 0.0008533, "bid": 0.0008375}, "AICO/USDT": {"last": 0.001353, "ask": 0.001356, "bid": 0.001331}, "TUSD/USDT": {"last": 0.9995, "ask": 0.9996, "bid": 0.9995}, "PANDA/USDT": {"last": 0.003982, "ask": 0.00413, "bid": 0.003961}, "FARM/USDT": {"last": 26.99, "ask": 27.09, "bid": 26.94}, "LRC/USDT": {"last": 0.28343, "ask": 0.2848, "bid": 0.28378}, "CHNG/USDT": {"last": 0.09975, "ask": 0.10012, "bid": 0.0997}, "RFOX/USDT": {"last": 0.00934, "ask": 0.00929, "bid": 0.0091}, "TRR/USDT": {"last": 0.1513, "ask": 0.166, "bid": 0.1528}, "PANDO/USDT": {"last": 0.006835, "ask": 0.006905, "bid": 0.006669}, "NTP/USDT": {"last": 0.03268, "ask": 0.03269, "bid": 0.03267}, "UPI/USDT": {"last": 0.001523, "ask": 0.00153, "bid": 0.001479}, "EKTA/USDT": {"last": 0.013261, "ask": 0.013579, "bid": 0.013265}, "CAI/USDT": {"last": 0.01261, "ask": 0.01261, "bid": 0.01259}, "OCTAVUS/USDT": {"last": 0.0008795, "ask": 0.0008794, "bid": 0.0008773}, "HAI/USDT": {"last": 0.02676, "ask": 0.02675, "bid": 0.0266}, "CWD/USDT": {"last": 0.0001291, "ask": 0.0001297, "bid": 0.0001291}, "BAR/USDT": {"last": 3.673, "ask": 3.693, "bid": 3.674}, "CEL/USDT": {"last": 0.2101, "ask": 0.2112, "bid": 0.2103}, "DKM/USDT": {"last": 6.206e-05, "ask": 6.6e-05, "bid": 6.206e-05}, "POP/USDT": {"last": 3.714e-05, "ask": 3.819e-05, "bid": 3.575e-05}, "UNW/USDT": {"last": 0.0785, "ask": 0.0776, "bid": 0.076}, "LTC/USDT": {"last": 79.73, "ask": 79.84, "bid": 79.81}, "WWY/USDT": {"last": 0.005685, "ask": 0.005769, "bid": 0.005666}, "ALI/USDT": {"last": 0.02254, "ask": 0.02297, "bid": 0.0226}, "OGV/USDT": {"last": 0.007719, "ask": 0.007724, "bid": 0.007713}, "VDR/USDT": {"last": 0.0004619, "ask": 0.0004619, "bid": 0.0004438}, "NODL/USDT": {"last": 0.002664, "ask": 0.002664, "bid": 0.002651}, "PICKLE/USDT": {"last": 1.1255, "ask": 1.1311, "bid": 1.122}, "PEPEAI/USDT": {"last": 5.5e-09, "ask": 5.5e-09, "bid": 5.426e-09}, "PENDULUM/USDT": {"last": 0.2526, "ask": 0.2526, "bid": 0.2525}, "PHM/USDT": {"last": 5.642e-05, "ask": 5.642e-05, "bid": 5.513e-05}, "XEND/USDT": {"last": 0.02435, "ask": 0.02499, "bid": 0.02429}, "TANK/USDT": {"last": 0.003634, "ask": 0.003679, "bid": 0.003621}, "BSPT/USDT": {"last": 0.0011282, "ask": 0.0011896, "bid": 0.0010888}, "JUSTICE/USDT": {"last": 4.362e-05, "ask": 4.521e-05, "bid": 4.357e-05}, "CLV/USDT": {"last": 0.04636, "ask": 0.04646, "bid": 0.04635}, "CELT/USDT": {"last": 6.306e-05, "ask": 6.392e-05, "bid": 6.285e-05}, "AWO/USDT": {"last": 0.0001, "ask": 0.0001, "bid": 9.9e-05}, "OJA/USDT": {"last": 0.0125, "ask": 0.01379, "bid": 0.01092}, "SLC/USDT": {"last": 0.0025, "ask": 0.002732, "bid": 0.0025}, "SYP/USDT": {"last": 0.00096, "ask": 0.000962, "bid": 0.000956}, "ATRI/USDT": {"last": 0.002844, "ask": 0.003033, "bid": 0.002847}, "SWINGBY/USDT": {"last": 0.001943, "ask": 0.001947, "bid": 0.00193}, "RICE/USDT": {"last": 0.0267, "ask": 0.02699, "bid": 0.02601}, "SRLTY/USDT": {"last": 0.0001833, "ask": 0.0001849, "bid": 0.0001785}, "MVRS/USDT": {"last": 9.44e-08, "ask": 9.859e-08, "bid": 9.267e-08}, "XTM/USDT": {"last": 0.01651, "ask": 0.01652, "bid": 0.0165}, "CRAZYPEPE/USDT": {"last": 1.0595e-08, "ask": 1.0684e-08, "bid": 1.0594e-08}, "DVI/USDT": {"last": 0.01299, "ask": 0.01339, "bid": 0.01297}, "MBP/USDT": {"last": 0.011253, "ask": 0.011408, "bid": 0.011225}, "UMAMI/USDT": {"last": 12.64, "ask": 13.19, "bid": 12.5}, "3P/USDT": {"last": 2.8e-08, "ask": 2.8e-08, "bid": 2.792e-08}, "ICHI/USDT": {"last": 2.757, "ask": 2.759, "bid": 2.735}, "BXEN/USDT": {"last": 2.861e-08, "ask": 2.868e-08, "bid": 2.837e-08}, "GNX/USDT": {"last": 0.002027, "ask": 0.002072, "bid": 0.002026}, "DODI/USDT": {"last": 0.000462, "ask": 0.000465, "bid": 0.000462}, "IRENA/USDT": {"last": 7.71e-06, "ask": 7.804e-06, "bid": 7.664e-06}, "ETH3S/USDT": {"last": 0.012816, "ask": 0.012858, "bid": 0.012831}, "ZEE/USDT": {"last": 0.02079, "ask": 0.0211, "bid": 0.02076}, "UBSN/USDT": {"last": 2.573e-05, "ask": 2.591e-05, "bid": 2.457e-05}, "FUN/USDT": {"last": 0.005036, "ask": 0.005037, "bid": 0.005033}, "FDC/USDT": {"last": 1.905e-07, "ask": 2.045e-07, "bid": 1.905e-07}, "REBUS/USDT": {"last": 0.01244, "ask": 0.01258, "bid": 0.01237}, "LON/USDT": {"last": 0.5476, "ask": 0.5501, "bid": 0.5466}, "BTC3L/USDT": {"last": 0.254643, "ask": 0.25554, "bid": 0.254476}, "JUNO/USDT": {"last": 0.59, "ask": 0.5928, "bid": 0.5892}, "ISP/USDT": {"last": 0.0009822, "ask": 0.0009968, "bid": 0.0009675}, "MMFARB/USDT": {"last": 0.0934, "ask": 0.0955, "bid": 0.0931}, "QUACK/USDT": {"last": 9.151e-10, "ask": 9.153e-10, "bid": 9.15e-10}, "AICODE/USDT": {"last": 6.5, "ask": 6.54, "bid": 6.39}, "ZPC/USDT": {"last": 2.962e-09, "ask": 2.994e-09, "bid": 2.962e-09}, "SWTH/USDT": {"last": 0.005814, "ask": 0.005978, "bid": 0.005796}, "BIN/USDT": {"last": 0.001384, "ask": 0.00144, "bid": 0.001358}, "BICO/USDT": {"last": 0.3096, "ask": 0.311, "bid": 0.3072}, "LOTT/USDT": {"last": 0.01541, "ask": 0.01542, "bid": 0.01282}, "SALO/USDT": {"last": 0.004026, "ask": 0.004189, "bid": 0.004027}, "GBC/USDT": {"last": 0.0016, "ask": 0.00163, "bid": 0.0016}, "FRTS/USDT": {"last": 0.0002131, "ask": 0.0002171, "bid": 0.0002114}, "MOONEY/USDT": {"last": 0.000678, "ask": 0.000683, "bid": 0.000675}, "SENSO/USDT": {"last": 0.05963, "ask": 0.05994, "bid": 0.05918}, "TRYB/USDT": {"last": 0.04478, "ask": 0.04494, "bid": 0.0448}, "ADAO/USDT": {"last": 0.00189, "ask": 0.00207, "bid": 0.00191}, "WING/USDT": {"last": 5.6554, "ask": 5.6726, "bid": 5.6451}, "LEMN/USDT": {"last": 0.00715, "ask": 0.00812, "bid": 0.00722}, "SBG/USDT": {"last": 1.7e-05, "ask": 1.7e-05, "bid": 1.4e-05}, "NAO/USDT": {"last": 2.291e-09, "ask": 2.485e-09, "bid": 2.281e-09}, "SHIDO/USDT": {"last": 0.0001097, "ask": 0.0001107, "bid": 0.0001095}, "VSYS/USDT": {"last": 0.001333, "ask": 0.0013563, "bid": 0.0013116}, "DEUS/USDT": {"last": 40.0, "ask": 41.9, "bid": 38.0}, "GMPD/USDT": {"last": 0.01339, "ask": 0.01349, "bid": 0.01318}, "ASTR/USDT": {"last": 0.05099, "ask": 0.05113, "bid": 0.05112}, "ORCA/USDT": {"last": 0.714, "ask": 0.7235, "bid": 0.7101}, "HAHA/USDT": {"last": 2.163e-05, "ask": 2.171e-05, "bid": 2.163e-05}, "WAS/USDT": {"last": 0.01556, "ask": 0.01555, "bid": 0.01541}, "ONG/USDT": {"last": 0.24242, "ask": 0.24422, "bid": 0.24051}, "FLUX/USDT": {"last": 0.4918, "ask": 0.4932, "bid": 0.492}, "CELO/USDT": {"last": 0.5172, "ask": 0.5186, "bid": 0.5171}, "RBX/USDT": {"last": 0.0486, "ask": 0.0491, "bid": 0.0487}, "XVG/USDT": {"last": 0.001894, "ask": 0.001901, "bid": 0.001893}, "BTS/USDT": {"last": 0.007945, "ask": 0.007975, "bid": 0.007936}, "GDO/USDT": {"last": 3.008e-08, "ask": 3.058e-08, "bid": 3.002e-08}, "EVMOS/USDT": {"last": 0.1988, "ask": 0.1998, "bid": 0.198}, "XEC/USDT": {"last": 2.688e-05, "ask": 2.689e-05, "bid": 2.682e-05}, "PIZA/USDT": {"last": 2.7416e-05, "ask": 2.7428e-05, "bid": 2.6011e-05}, "LUFC/USDT": {"last": 0.7651, "ask": 0.7657, "bid": 0.7396}, "UNM/USDT": {"last": 36.0156, "ask": 36.0867, "bid": 36.0149}, "GUILD/USDT": {"last": 0.005717, "ask": 0.005734, "bid": 0.005699}, "GLEEC/USDT": {"last": 0.0405, "ask": 0.04084, "bid": 0.0405}, "SFP/USDT": {"last": 0.3953, "ask": 0.3963, "bid": 0.3954}, "GNO/USDT": {"last": 109.43, "ask": 109.63, "bid": 108.6}, "EPX/USDT": {"last": 0.0002436, "ask": 0.0002445, "bid": 0.0002438}, "TOWN/USDT": {"last": 0.02397, "ask": 0.02397, "bid": 0.02353}, "MLTPX/USDT": {"last": 1.07e-06, "ask": 1.1e-06, "bid": 1.05e-06}, "BAS/USDT": {"last": 0.03103, "ask": 0.03131, "bid": 0.03079}, "SHOPX/USDT": {"last": 0.010354, "ask": 0.010639, "bid": 0.010287}, "ASTRAFER/USDT": {"last": 1.023, "ask": 1.039, "bid": 1.03}, "DF/USDT": {"last": 0.04526, "ask": 0.04551, "bid": 0.04525}, "TPT/USDT": {"last": 0.009487, "ask": 0.009591, "bid": 0.00948}, "MXT/USDT": {"last": 0.0011852, "ask": 0.0011936, "bid": 0.0011741}, "REVO/USDT": {"last": 0.10118, "ask": 0.10188, "bid": 0.10065}, "FINA/USDT": {"last": 0.02048, "ask": 0.02062, "bid": 0.02049}, "SPELL/USDT": {"last": 0.0005617, "ask": 0.0005646, "bid": 0.0005616}, "XPX/USDT": {"last": 0.000707, "ask": 0.000714, "bid": 0.0007029}, "SD/USDT": {"last": 0.9307, "ask": 0.9307, "bid": 0.9229}, "CFI/USDT": {"last": 1.45e-07, "ask": 1.607e-07, "bid": 1.409e-07}, "BITCI/USDT": {"last": 0.003285, "ask": 0.003334, "bid": 0.003219}, "NMR/USDT": {"last": 13.254, "ask": 13.3, "bid": 13.254}, "YVS/USDT": {"last": 0.05313, "ask": 0.05396, "bid": 0.05293}, "VVS/USDT": {"last": 3.058e-06, "ask": 3.125e-06, "bid": 3.057e-06}, "USTC/USDT": {"last": 0.014879, "ask": 0.014967, "bid": 0.01491}, "HNS/USDT": {"last": 0.02039, "ask": 0.02097, "bid": 0.02039}, "LTC3S/USDT": {"last": 0.034902, "ask": 0.034998, "bid": 0.034927}, "MEE/USDT": {"last": 0.004247, "ask": 0.004269, "bid": 0.004193}, "HPX/USDT": {"last": 0.01405, "ask": 0.01423, "bid": 0.01359}, "CVT/USDT": {"last": 0.00023, "ask": 0.0002384, "bid": 0.0002293}, "TLOS/USDT": {"last": 0.17265, "ask": 0.17304, "bid": 0.17162}, "MONI/USDT": {"last": 0.01658, "ask": 0.01661, "bid": 0.01632}, "TEDDY/USDT": {"last": 1.751e-09, "ask": 1.751e-09, "bid": 1.716e-09}, "NEOFI/USDT": {"last": 0.001017, "ask": 0.001021, "bid": 0.00101}, "BRN/USDT": {"last": 0.1104, "ask": 0.1108, "bid": 0.1101}, "ALM/USDT": {"last": 0.004722, "ask": 0.004721, "bid": 0.0047}, "XCT/USDT": {"last": 0.005276, "ask": 0.005331, "bid": 0.005247}, "SDAO/USDT": {"last": 0.324, "ask": 0.326, "bid": 0.324}, "AI/USDT": {"last": 0.000226, "ask": 0.0002296, "bid": 0.000226}, "SUN/USDT": {"last": 0.005356, "ask": 0.005363, "bid": 0.005356}, "ORBR/USDT": {"last": 1.565343, "ask": 1.594157, "bid": 1.402306}, "SUKU/USDT": {"last": 0.05942, "ask": 0.05969, "bid": 0.05938}, "ATPAY/USDT": {"last": 0.3864, "ask": 0.3864, "bid": 0.3819}, "AAVE/USDT": {"last": 62.325, "ask": 62.4284, "bid": 62.3248}, "RADAR/USDT": {"last": 0.006672, "ask": 0.00668, "bid": 0.006662}, "MENGO/USDT": {"last": 0.4427, "ask": 0.4448, "bid": 0.4412}, "TIGER/USDT": {"last": 1.631e-09, "ask": 1.7124e-09, "bid": 1.6036e-09}, "PPIZZA/USDT": {"last": 4.4e-06, "ask": 4.46e-06, "bid": 4.4e-06}, "TXA/USDT": {"last": 0.3362, "ask": 0.3363, "bid": 0.3362}, "ZKS/USDT": {"last": 0.04705, "ask": 0.0472, "bid": 0.04685}, "ABBC/USDT": {"last": 0.08733, "ask": 0.08772, "bid": 0.08727}, "BURGER/USDT": {"last": 0.463, "ask": 0.4641, "bid": 0.4623}, "TURBO/USDT": {"last": 0.000745, "ask": 0.0007459, "bid": 0.000745}, "SFIN/USDT": {"last": 710.39, "ask": 719.72, "bid": 706.73}, "JST/USDT": {"last": 0.02307485, "ask": 0.02314966, "bid": 0.02308624}, "BLY/USDT": {"last": 0.00342, "ask": 0.003448, "bid": 0.003366}, "NCT/USDT": {"last": 0.009012, "ask": 0.009076, "bid": 0.008985}, "FUNFI/USDT": {"last": 2.21e-10, "ask": 2.269e-10, "bid": 2.21e-10}, "JULD/USDT": {"last": 0.002269, "ask": 0.002291, "bid": 0.002265}, "HADES/USDT": {"last": 0.236, "ask": 0.239, "bid": 0.236}, "POLIS/USDT": {"last": 0.1633, "ask": 0.1669, "bid": 0.1633}, "XRPAYNET/USDT": {"last": 0.000697, "ask": 0.0007, "bid": 0.000696}, "RANKER/USDT": {"last": 0.002608, "ask": 0.002696, "bid": 0.00257}, "AMPL/USDT": {"last": 1.014886, "ask": 1.017389, "bid": 0.995004}, "BLP/USDT": {"last": 0.06048, "ask": 0.061, "bid": 0.05983}, "KINT/USDT": {"last": 0.6578, "ask": 0.6578, "bid": 0.6538}, "BUNNY/USDT": {"last": 0.09253, "ask": 0.09342, "bid": 0.09248}, "XDAO/USDT": {"last": 0.6357, "ask": 0.64, "bid": 0.6342}, "TRU1/USDT": {"last": 0.10255, "ask": 0.10289, "bid": 0.1025}, "ASVA/USDT": {"last": 0.00836, "ask": 0.00843, "bid": 0.00833}, "HOD/USDT": {"last": 0.00198, "ask": 0.00199, "bid": 0.001978}, "MESA/USDT": {"last": 0.000861, "ask": 0.001039, "bid": 0.000874}, "TOWER/USDT": {"last": 0.002604, "ask": 0.002615, "bid": 0.002584}, "POSI/USDT": {"last": 0.02708, "ask": 0.02749, "bid": 0.02659}, "PAINT/USDT": {"last": 0.0006125, "ask": 0.0006125, "bid": 0.00059223}, "EL/USDT": {"last": 0.002205, "ask": 0.002215, "bid": 0.002184}, "EDG/USDT": {"last": 0.0003155, "ask": 0.0003228, "bid": 0.0003145}, "BABYDOGE/USDT": {"last": 2.2654e-09, "ask": 2.2648e-09, "bid": 2.259e-09}, "RIO/USDT": {"last": 0.1325, "ask": 0.133, "bid": 0.1322}, "AVXL/USDT": {"last": 0.0001372, "ask": 0.00014155, "bid": 0.00013537}, "GFT/USDT": {"last": 0.01789, "ask": 0.018, "bid": 0.01796}, "SUNNY/USDT": {"last": 3.224e-05, "ask": 3.349e-05, "bid": 3.209e-05}, "MANC/USDT": {"last": 0.82, "ask": 0.8203, "bid": 0.8049}, "DICE/USDT": {"last": 0.03526, "ask": 0.0358, "bid": 0.03526}, "XTZ/USDT": {"last": 0.88169, "ask": 0.88409, "bid": 0.88169}, "TRIBE/USDT": {"last": 0.2837, "ask": 0.2873, "bid": 0.2791}, "HYCO/USDT": {"last": 0.3197, "ask": 0.32, "bid": 0.3186}, "MDT/USDT": {"last": 0.00815, "ask": 0.00819, "bid": 0.00804}, "FYN/USDT": {"last": 0.04043, "ask": 0.04104, "bid": 0.04068}, "NEW/USDT": {"last": 4.736e-05, "ask": 4.775e-05, "bid": 4.732e-05}, "MITX/USDT": {"last": 0.00035, "ask": 0.00038, "bid": 0.00035}, "OATH/USDT": {"last": 0.1018, "ask": 0.1054, "bid": 0.1013}, "GERA/USDT": {"last": 0.004661, "ask": 0.00467, "bid": 0.004637}, "HEART/USDT": {"last": 0.015429, "ask": 0.015431, "bid": 0.015425}, "MNTL/USDT": {"last": 0.00504, "ask": 0.00507, "bid": 0.00501}, "VOLT/USDT": {"last": 8.408e-07, "ask": 8.409e-07, "bid": 8.405e-07}, "DTO/USDT": {"last": 0.008501, "ask": 0.008996, "bid": 0.0085}, "CHANGE/USDT": {"last": 0.01037, "ask": 0.0104, "bid": 0.0103}, "COCOS/USDT": {"last": 1.26, "ask": 1.2617, "bid": 1.261}, "EYES/USDT": {"last": 0.0014, "ask": 0.00141, "bid": 0.00139}, "ATP/USDT": {"last": 0.04563, "ask": 0.04644, "bid": 0.04521}, "IDIA/USDT": {"last": 0.03652, "ask": 0.03751, "bid": 0.03727}, "BETA/USDT": {"last": 0.09833, "ask": 0.09862, "bid": 0.09855}, "MARS4/USDT": {"last": 0.000657, "ask": 0.0006702, "bid": 0.0006552}, "AGLD/USDT": {"last": 0.365, "ask": 0.3672, "bid": 0.3647}, "EJS/USDT": {"last": 0.004456, "ask": 0.004478, "bid": 0.004432}, "TOOB/USDT": {"last": 0.001337, "ask": 0.001337, "bid": 0.00123}, "AKITA/USDT": {"last": 1.2701e-07, "ask": 1.275e-07, "bid": 1.2656e-07}, "AURORA/USDT": {"last": 0.1309, "ask": 0.1311, "bid": 0.1305}, "LOST/USDT": {"last": 0.03286, "ask": 0.03394, "bid": 0.03182}, "SRT1/USDT": {"last": 2.0385, "ask": 2.0387, "bid": 2.0368}, "FMT/USDT": {"last": 0.0085, "ask": 0.00939, "bid": 0.00852}, "KUBE/USDT": {"last": 0.007723, "ask": 0.007748, "bid": 0.007595}, "MMETA/USDT": {"last": 0.0145, "ask": 0.01483, "bid": 0.01447}, "SKP/USDT": {"last": 0.01359, "ask": 0.01354, "bid": 0.01335}, "NTX/USDT": {"last": 0.03723, "ask": 0.03831, "bid": 0.03723}, "SAMO/USDT": {"last": 0.00294, "ask": 0.002944, "bid": 0.002918}, "SSS/USDT": {"last": 0.1241, "ask": 0.1263, "bid": 0.124}, "PC/USDT": {"last": 0.002853, "ask": 0.002854, "bid": 0.002845}, "POGAI/USDT": {"last": 7.371e-05, "ask": 7.414e-05, "bid": 7.368e-05}, "BERRY/USDT": {"last": 0.0007737, "ask": 0.0007835, "bid": 0.0007706}, "TORN/USDT": {"last": 6.019, "ask": 6.029, "bid": 6.0}, "DAPPT/USDT": {"last": 0.0003183, "ask": 0.0003277, "bid": 0.0003166}, "KAI/USDT": {"last": 0.007252, "ask": 0.007327, "bid": 0.00725}, "DCR/USDT": {"last": 17.38717, "ask": 17.53356, "bid": 17.30526}, "1INCH/USDT": {"last": 0.4112, "ask": 0.4116, "bid": 0.4103}, "NBT/USDT": {"last": 0.002853, "ask": 0.002855, "bid": 0.002853}, "GAL/USDT": {"last": 1.434, "ask": 1.44, "bid": 1.436}, "GLMR/USDT": {"last": 0.2848, "ask": 0.2852, "bid": 0.2846}, "OOE/USDT": {"last": 0.01811, "ask": 0.01818, "bid": 0.01802}, "VEX/USDT": {"last": 0.001239, "ask": 0.001239, "bid": 0.001225}, "FARB/USDT": {"last": 0.0027, "ask": 0.0027, "bid": 0.002669}, "POKT/USDT": {"last": 0.04094, "ask": 0.04116, "bid": 0.04099}, "AAG/USDT": {"last": 0.005026, "ask": 0.005065, "bid": 0.004966}, "EDU/USDT": {"last": 1.07991, "ask": 1.08404, "bid": 1.08139}, "CENNZ/USDT": {"last": 0.00866, "ask": 0.00882, "bid": 0.00852}, "ARCH/USDT": {"last": 6.16, "ask": 6.19, "bid": 6.15}, "ONTP/USDT": {"last": 0.03027, "ask": 0.03041, "bid": 0.03025}, "ANA/USDT": {"last": 0.09548, "ask": 0.09726, "bid": 0.09476}, "SFTY/USDT": {"last": 0.03845, "ask": 0.03847, "bid": 0.03845}, "PRIME/USDT": {"last": 1.304, "ask": 1.306, "bid": 1.3}, "SRS/USDT": {"last": 0.0005089, "ask": 0.000527, "bid": 0.0005092}, "ADAX/USDT": {"last": 0.004684, "ask": 0.004917, "bid": 0.00472}, "SONAR/USDT": {"last": 0.005666, "ask": 0.005762, "bid": 0.005596}, "SLIM/USDT": {"last": 0.03832, "ask": 0.03911, "bid": 0.03825}, "KOIN/USDT": {"last": 0.5613, "ask": 0.5613, "bid": 0.5612}, "SPUME/USDT": {"last": 0.01235, "ask": 0.01253, "bid": 0.01229}, "HANDY/USDT": {"last": 0.000857, "ask": 0.000916, "bid": 0.00085}, "CVTX/USDT": {"last": 0.1073, "ask": 0.1073, "bid": 0.1072}, "NABOX/USDT": {"last": 5.847e-06, "ask": 5.847e-06, "bid": 5.657e-06}, "FON/USDT": {"last": 0.585, "ask": 0.5859, "bid": 0.5843}, "DPR/USDT": {"last": 0.00657, "ask": 0.006693, "bid": 0.006557}, "HOPR/USDT": {"last": 0.05525, "ask": 0.05635, "bid": 0.0552}, "ML/USDT": {"last": 0.0914, "ask": 0.0918, "bid": 0.0901}, "SPIRIT/USDT": {"last": 0.004095, "ask": 0.0041, "bid": 0.004084}, "LEVER/USDT": {"last": 0.00143, "ask": 0.001439, "bid": 0.001429}, "INV/USDT": {"last": 32.44, "ask": 33.35, "bid": 32.38}, "LAYER/USDT": {"last": 0.07714, "ask": 0.07734, "bid": 0.07494}, "TPC/USDT": {"last": 0.0004, "ask": 0.00041, "bid": 0.0004}, "PLAY/USDT": {"last": 0.06354, "ask": 0.06472, "bid": 0.06359}, "HAO/USDT": {"last": 0.00343, "ask": 0.00349, "bid": 0.00337}, "DAO/USDT": {"last": 1.4707, "ask": 1.4781, "bid": 1.4701}, "CGPT/USDT": {"last": 0.152565, "ask": 0.153595, "bid": 0.152568}, "EMP/USDT": {"last": 0.03572, "ask": 0.03687, "bid": 0.0343}, "APD/USDT": {"last": 0.01483, "ask": 0.01502, "bid": 0.01482}, "MBOX/USDT": {"last": 0.4056, "ask": 0.4065, "bid": 0.4051}, "WNT/USDT": {"last": 0.038443, "ask": 0.038504, "bid": 0.038346}, "GOO/USDT": {"last": 0.01412, "ask": 0.0144, "bid": 0.01407}, "BBS/USDT": {"last": 0.01492, "ask": 0.01551, "bid": 0.01485}, "WMINIMA/USDT": {"last": 0.0382, "ask": 0.0387, "bid": 0.0384}, "DEXE/USDT": {"last": 2.596, "ask": 2.599, "bid": 2.587}, "CAN/USDT": {"last": 0.000238, "ask": 0.000241, "bid": 0.0002371}, "MULTI/USDT": {"last": 7.931, "ask": 7.943, "bid": 7.896}, "REDLC/USDT": {"last": 0.0691, "ask": 0.0692, "bid": 0.0681}, "NSURE/USDT": {"last": 0.009752, "ask": 0.009803, "bid": 0.009697}, "NXD/USDT": {"last": 0.000306, "ask": 0.000307, "bid": 0.000303}, "HOP/USDT": {"last": 0.08625, "ask": 0.0873, "bid": 0.08535}, "TRIVIA/USDT": {"last": 0.001848, "ask": 0.001865, "bid": 0.001833}, "CPOS/USDT": {"last": 8.058e-07, "ask": 8.124e-07, "bid": 7.96e-07}, "YODE/USDT": {"last": 0.01183, "ask": 0.01367, "bid": 0.0114}, "CT/USDT": {"last": 0.000105, "ask": 0.00011, "bid": 0.000105}, "SUTER/USDT": {"last": 0.0003776, "ask": 0.0003776, "bid": 0.0003674}, "HAPI/USDT": {"last": 10.722, "ask": 10.743, "bid": 10.519}, "PVT/USDT": {"last": 4.646e-06, "ask": 4.684e-06, "bid": 4.6e-06}, "SPWN/USDT": {"last": 0.0002443, "ask": 0.0002727, "bid": 0.0002178}, "TAO1/USDT": {"last": 0.06967, "ask": 0.07073, "bid": 0.06941}, "HORD/USDT": {"last": 0.02275, "ask": 0.02365, "bid": 0.02259}, "XWG/USDT": {"last": 0.0011747, "ask": 0.0012049, "bid": 0.00118}, "ICB/USDT": {"last": 0.00165, "ask": 0.001643, "bid": 0.001612}, "SOV/USDT": {"last": 3.69e-08, "ask": 3.88e-08, "bid": 3.73e-08}, "FEN/USDT": {"last": 9.1e-08, "ask": 9.7e-08, "bid": 9.1e-08}, "PORTUMA/USDT": {"last": 0.0002558, "ask": 0.0002568, "bid": 0.0002522}, "RARI/USDT": {"last": 1.3804, "ask": 1.3871, "bid": 1.3692}, "SYN/USDT": {"last": 0.6111, "ask": 0.6126, "bid": 0.6111}, "BTRST/USDT": {"last": 0.762, "ask": 0.763, "bid": 0.762}, "ATLAS/USDT": {"last": 0.002126, "ask": 0.00213, "bid": 0.002116}, "QUIDD/USDT": {"last": 0.01294, "ask": 0.01339, "bid": 0.01281}, "HT/USDT": {"last": 2.733, "ask": 2.735, "bid": 2.722}, "XYO/USDT": {"last": 0.004061, "ask": 0.004064, "bid": 0.003982}, "BeyondFi/USDT": {"last": 0.005681, "ask": 0.005901, "bid": 0.005675}, "SKILL/USDT": {"last": 0.5807, "ask": 0.5957, "bid": 0.5799}, "SAMA/USDT": {"last": 0.01677, "ask": 0.01708, "bid": 0.01672}, "USDC/USDT": {"last": 0.9996, "ask": 0.9996, "bid": 0.9995}, "REAL/USDT": {"last": 0.08028, "ask": 0.08107, "bid": 0.07945}, "GEL/USDT": {"last": 0.2622, "ask": 0.2655, "bid": 0.2612}, "DVRS/USDT": {"last": 8.033e-05, "ask": 8.594e-05, "bid": 8.034e-05}, "PENDLE/USDT": {"last": 0.37637, "ask": 0.37814, "bid": 0.37603}, "ETP/USDT": {"last": 0.02238, "ask": 0.02242, "bid": 0.02226}, "ROG/USDT": {"last": 0.2273, "ask": 0.2659, "bid": 0.2212}, "ARGON/USDT": {"last": 0.0015695, "ask": 0.0015802, "bid": 0.0015492}, "GQ/USDT": {"last": 0.004167, "ask": 0.004115, "bid": 0.004052}, "YGG/USDT": {"last": 0.17665, "ask": 0.17721, "bid": 0.17665}, "HI/USDT": {"last": 0.00443, "ask": 0.00443, "bid": 0.00441}, "TGT/USDT": {"last": 0.00742, "ask": 0.00743, "bid": 0.00739}, "HUSL/USDT": {"last": 0.0195, "ask": 0.01954, "bid": 0.01953}, "HEX/USDT": {"last": 0.05946, "ask": 0.06066, "bid": 0.05829}, "STN/USDT": {"last": 0.002221, "ask": 0.002224, "bid": 0.002221}, "ZZ/USDT": {"last": 0.2762, "ask": 0.2764, "bid": 0.2761}, "BPRIVA/USDT": {"last": 0.2105, "ask": 0.2146, "bid": 0.2099}, "GMT/USDT": {"last": 0.27, "ask": 0.27, "bid": 0.2693}, "GSTBSC/USDT": {"last": 0.01632, "ask": 0.01646, "bid": 0.01618}, "JT/USDT": {"last": 0.04916, "ask": 0.05097, "bid": 0.0486}, "COGO/USDT": {"last": 0.000231, "ask": 0.00023, "bid": 0.000203}, "EQ/USDT": {"last": 0.0003993, "ask": 0.000399, "bid": 0.000395}, "NEO/USDT": {"last": 8.997, "ask": 9.008, "bid": 8.994}, "MLN/USDT": {"last": 18.326, "ask": 18.465, "bid": 18.316}, "XRD/USDT": {"last": 0.07368, "ask": 0.07417, "bid": 0.07359}, "COW/USDT": {"last": 0.0673, "ask": 0.06853, "bid": 0.0672}, "PATH/USDT": {"last": 0.006532, "ask": 0.006581, "bid": 0.00651}, "MHUNT/USDT": {"last": 0.00946, "ask": 0.00948, "bid": 0.0094}, "UMA/USDT": {"last": 2.357, "ask": 2.36, "bid": 2.35}, "MOVR/USDT": {"last": 6.355, "ask": 6.393, "bid": 6.354}, "FTN/USDT": {"last": 0.8264, "ask": 0.8265, "bid": 0.8247}, "ENS/USDT": {"last": 10.284, "ask": 10.291, "bid": 10.27}, "XPR/USDT": {"last": 0.000995, "ask": 0.001002, "bid": 0.000996}, "STAR1/USDT": {"last": 0.02005, "ask": 0.02237, "bid": 0.01996}, "DMD/USDT": {"last": 7.069, "ask": 7.088, "bid": 7.051}, "ATID/USDT": {"last": 0.00206, "ask": 0.00211, "bid": 0.00205}, "CTC/USDT": {"last": 0.3222, "ask": 0.3229, "bid": 0.3227}, "KAR/USDT": {"last": 0.08299, "ask": 0.08405, "bid": 0.08285}, "QUA/USDT": {"last": 0.00554, "ask": 0.005588, "bid": 0.00544}, "INTR/USDT": {"last": 0.02122, "ask": 0.02152, "bid": 0.02118}, "COFIX/USDT": {"last": 0.02745, "ask": 0.0275, "bid": 0.02738}, "PKN/USDT": {"last": 0.001397, "ask": 0.001402, "bid": 0.001386}, "TOMS/USDT": {"last": 0.002304, "ask": 0.002304, "bid": 0.002295}, "NXRA/USDT": {"last": 0.05949, "ask": 0.05998, "bid": 0.05951}, "RCG/USDT": {"last": 0.1012, "ask": 0.1024, "bid": 0.0985}, "PXT/USDT": {"last": 0.8609, "ask": 0.8643, "bid": 0.8602}, "SGB/USDT": {"last": 0.0079668, "ask": 0.0080471, "bid": 0.0078792}, "AZIT/USDT": {"last": 0.1171, "ask": 0.1176, "bid": 0.1166}, "OPP/USDT": {"last": 0.00633, "ask": 0.00655, "bid": 0.00633}, "SUDO/USDT": {"last": 0.5531, "ask": 0.5581, "bid": 0.5493}, "DFL/USDT": {"last": 0.0007107, "ask": 0.0007319, "bid": 0.0007103}, "BABY/USDT": {"last": 0.01775, "ask": 0.01794, "bid": 0.01768}, "TOKE/USDT": {"last": 0.6878, "ask": 0.6883, "bid": 0.687}, "RLTM/USDT": {"last": 0.02411, "ask": 0.02418, "bid": 0.02411}, "NAKA/USDT": {"last": 0.2061, "ask": 0.2062, "bid": 0.2044}, "RED/USDT": {"last": 7.63e-05, "ask": 7.64e-05, "bid": 7.62e-05}, "CQT/USDT": {"last": 0.12809, "ask": 0.12831, "bid": 0.12752}, "NPAS/USDT": {"last": 0.01636, "ask": 0.01712, "bid": 0.01617}, "RILLA/USDT": {"last": 0.001653, "ask": 0.001659, "bid": 0.001651}, "LBP/USDT": {"last": 0.0002095, "ask": 0.0002103, "bid": 0.0002086}, "ETHF/USDT": {"last": 0.1241, "ask": 0.1252, "bid": 0.1224}, "WSPP/USDT": {"last": 1.2327e-05, "ask": 1.238e-05, "bid": 1.22e-05}, "AMD/USDT": {"last": 1.1793e-10, "ask": 1.1792e-10, "bid": 1.1788e-10}, "MOTG/USDT": {"last": 0.0295, "ask": 0.0294, "bid": 0.0293}, "MEGA/USDT": {"last": 0.3795, "ask": 0.3795, "bid": 0.377}, "ACA/USDT": {"last": 0.057, "ask": 0.05718, "bid": 0.05702}, "U/USDT": {"last": 0.0001862, "ask": 0.0001886, "bid": 0.0001829}, "HUNT/USDT": {"last": 0.3236, "ask": 0.3242, "bid": 0.3205}, "POINT/USDT": {"last": 0.0274, "ask": 0.02879, "bid": 0.02741}, "METFI/USDT": {"last": 2.658, "ask": 2.68, "bid": 2.64}, "MEGALAND/USDT": {"last": 5.898e-10, "ask": 5.947e-10, "bid": 5.866e-10}, "PNK/USDT": {"last": 0.02617, "ask": 0.02622, "bid": 0.02615}, "HARL/USDT": {"last": 0.0002335, "ask": 0.0002404, "bid": 0.0002311}, "URD/USDT": {"last": 0.01344, "ask": 0.01518, "bid": 0.01344}, "YFX/USDT": {"last": 0.05131, "ask": 0.05189, "bid": 0.05134}, "MFAM/USDT": {"last": 0.001333, "ask": 0.001339, "bid": 0.001327}, "DANA/USDT": {"last": 0.002569, "ask": 0.00269, "bid": 0.002569}, "TLC/USDT": {"last": 15.58, "ask": 15.67, "bid": 15.53}, "CHAMP1/USDT": {"last": 0.0165, "ask": 0.01662, "bid": 0.01636}, "BRE/USDT": {"last": 0.00112, "ask": 0.001145, "bid": 0.001083}, "OCEAN/USDT": {"last": 0.33206, "ask": 0.33262, "bid": 0.33194}, "BCB/USDT": {"last": 0.00418, "ask": 0.0042, "bid": 0.00416}, "BSV/USDT": {"last": 34.8748, "ask": 34.905, "bid": 34.8351}, "SRK/USDT": {"last": 0.0002189, "ask": 0.0002199, "bid": 0.0002112}, "STRIP/USDT": {"last": 0.01502, "ask": 0.0151, "bid": 0.01493}, "GHST/USDT": {"last": 0.9231, "ask": 0.9301, "bid": 0.9216}, "NADA/USDT": {"last": 0.0005, "ask": 0.0005, "bid": 0.000457}, "CELR/USDT": {"last": 0.019004, "ask": 0.019081, "bid": 0.019019}, "ILV/USDT": {"last": 45.047, "ask": 45.168, "bid": 45.1}, "ATOR/USDT": {"last": 0.1286, "ask": 0.1287, "bid": 0.1284}, "MOVD/USDT": {"last": 0.000231, "ask": 0.000239, "bid": 0.000233}, "TREEB/USDT": {"last": 0.0099, "ask": 0.0101, "bid": 0.00983}, "EVE/USDT": {"last": 0.00694, "ask": 0.00697, "bid": 0.00692}, "MELD/USDT": {"last": 0.02116, "ask": 0.02116, "bid": 0.02115}, "YOOSHI/USDT": {"last": 6.335e-08, "ask": 6.415e-08, "bid": 6.284e-08}, "FRONT/USDT": {"last": 0.172131, "ask": 0.172357, "bid": 0.171716}, "OHM/USDT": {"last": 54.67, "ask": 55.48, "bid": 54.56}, "STKT/USDT": {"last": 0.000691, "ask": 0.000707, "bid": 0.000685}, "DBL/USDT": {"last": 0.00583, "ask": 0.005938, "bid": 0.0058}, "UFO/USDT": {"last": 1.0448e-06, "ask": 1.0611e-06, "bid": 1.0353e-06}, "AC/USDT": {"last": 0.0785, "ask": 0.0852, "bid": 0.0784}, "PAWSWAP/USDT": {"last": 1.57e-08, "ask": 1.631e-08, "bid": 1.58e-08}, "TOKAMAK/USDT": {"last": 1.55, "ask": 1.611, "bid": 1.531}, "BLS/USDT": {"last": 0.7302, "ask": 0.7421, "bid": 0.7216}, "SANTOS/USDT": {"last": 3.938, "ask": 3.951, "bid": 3.941}, "FUSE/USDT": {"last": 0.06789, "ask": 0.06808, "bid": 0.06778}, "CRT/USDT": {"last": 0.02849, "ask": 0.02851, "bid": 0.02847}, "APX/USDT": {"last": 0.04804, "ask": 0.04815, "bid": 0.04794}, "DFYN/USDT": {"last": 0.03289, "ask": 0.0334, "bid": 0.03272}, "MEFA/USDT": {"last": 8.325e-05, "ask": 8.343e-05, "bid": 8.149e-05}, "CULT/USDT": {"last": 3.663e-06, "ask": 3.683e-06, "bid": 3.651e-06}, "WGRT/USDT": {"last": 0.002477, "ask": 0.002496, "bid": 0.002463}, "CNC/USDT": {"last": 4.75, "ask": 4.801, "bid": 4.7}, "ICE/USDT": {"last": 0.005724, "ask": 0.00586, "bid": 0.005725}, "SPORT/USDT": {"last": 0.01476, "ask": 0.01484, "bid": 0.01469}, "DKA/USDT": {"last": 0.03123, "ask": 0.03176, "bid": 0.03107}, "FreeRossDAO/USDT": {"last": 5.719e-05, "ask": 5.743e-05, "bid": 5.7e-05}, "YLDY/USDT": {"last": 7.11e-05, "ask": 7.14e-05, "bid": 7.11e-05}, "SCRT/USDT": {"last": 0.5038, "ask": 0.5063, "bid": 0.5037}, "TMT/USDT": {"last": 0.1422, "ask": 0.1436, "bid": 0.142}, "DC/USDT": {"last": 0.0009349, "ask": 0.0009352, "bid": 0.0009297}, "MUDOL2/USDT": {"last": 0.02688, "ask": 0.02694, "bid": 0.02621}, "MONOX/USDT": {"last": 0.0671, "ask": 0.06711, "bid": 0.06488}, "CRF/USDT": {"last": 0.0019039, "ask": 0.0019078, "bid": 0.0018491}, "QI/USDT": {"last": 0.01098, "ask": 0.01105, "bid": 0.01082}, "PUSH/USDT": {"last": 0.3145, "ask": 0.3174, "bid": 0.313}, "FWC/USDT": {"last": 3.335e-11, "ask": 3.352e-11, "bid": 3.334e-11}, "GF/USDT": {"last": 0.08083, "ask": 0.08095, "bid": 0.08057}, "VRS/USDT": {"last": 0.026, "ask": 0.02777, "bid": 0.0261}, "EVRY/USDT": {"last": 0.00661, "ask": 0.00662, "bid": 0.00661}, "WEMIX/USDT": {"last": 0.7182, "ask": 0.7199, "bid": 0.718}, "PACHA/USDT": {"last": 7.751e-05, "ask": 7.923e-05, "bid": 7.723e-05}, "HBAR/USDT": {"last": 0.05161, "ask": 0.05181, "bid": 0.05157}, "VINU/USDT": {"last": 9.908e-09, "ask": 9.974e-09, "bid": 9.883e-09}, "CC/USDT": {"last": 0.0003, "ask": 0.000295, "bid": 0.000289}, "STARS/USDT": {"last": 0.0015, "ask": 0.001505, "bid": 0.001474}, "GFI/USDT": {"last": 0.000617, "ask": 0.000619, "bid": 0.000611}, "AAA/USDT": {"last": 6.736e-06, "ask": 6.751e-06, "bid": 6.59e-06}, "SUSHI/USDT": {"last": 0.8777, "ask": 0.88, "bid": 0.8778}, "YAG/USDT": {"last": 3.589e-05, "ask": 3.704e-05, "bid": 3.546e-05}, "PEAK/USDT": {"last": 0.001941, "ask": 0.001947, "bid": 0.001937}, "NESTA/USDT": {"last": 9.12e-05, "ask": 9.12e-05, "bid": 8.04e-05}, "YOM/USDT": {"last": 0.01657, "ask": 0.01658, "bid": 0.01647}, "DOR/USDT": {"last": 0.0002285, "ask": 0.0002319, "bid": 0.0002218}, "PERC/USDT": {"last": 0.1742, "ask": 0.1753, "bid": 0.1738}, "RIBBIT/USDT": {"last": 1.866e-08, "ask": 1.97e-08, "bid": 1.866e-08}, "WIN/USDT": {"last": 7.481e-05, "ask": 7.495e-05, "bid": 7.471e-05}, "SERP/USDT": {"last": 0.001353, "ask": 0.001381, "bid": 0.001345}, "BC/USDT": {"last": 0.00627, "ask": 0.00702, "bid": 0.00628}, "MXEN/USDT": {"last": 2.9133e-08, "ask": 2.9113e-08, "bid": 2.9e-08}}